Workbook

Sheet Read Me
A1: NEO PSP Financial Modelling Framework — Workbook Guide
B3: Purpose
B4: This workbook is a structural skeleton for the NEO PSP 3–5 year financial business case. It contains no confidential Banglalink or VEON figures. Yellow-filled cells are analyst inputs; illustrative placeholder values (clearly marked) show the expected format only — they must be replaced with real inputs before this model is used for decision-making.
B7: Color legend
B8: Yellow fill, blue text | D8: → Analyst input / assumption — edit these
B9: Black text | D9: → Formula, same-sheet calculation — do not hardcode over these
B10: Green text | D10: → Link pulling from another tab
B11: Coral header | D11: → Section label within a tab
B14: Tab structure
B15: 1. Assumptions - Revenue | C15: Revenue driver inputs by scenario: MDR, disbursement fees, remittance fees, gateway fees, referral fees
B16: 2. Assumptions - Cost | C16: Cost driver inputs by scenario: CAC, platform cost, compliance cost, headcount, settlement fees
B17: 3. Growth - Cust & Merchants | C17: Quarterly customer/merchant acquisition, churn, and active-base build, Y1–Y3
B18: 4. Transaction Volume Build | C18: Converts customer/merchant base into transaction volume and value by product line
B19: 5. Revenue Build | C19: Applies revenue drivers to transaction volume to build the revenue line by stream
B20: 6. Cost Build | C20: Applies cost drivers to volume/headcount to build the cost line by category
B21: 7. P&L Summary | C21: Consolidated 3-year P&L, EBITDA, breakeven marker, payback period
B22: 8. Scenario Control | C22: Single dropdown driving Conservative / Base / Aggressive across all tabs
B23: 9. Sensitivity Analysis | C23: Two-variable grid: merchant acquisition pace x MDR, output = Year 3 EBITDA
B24: 10. KPI Dashboard | C24: The 6 governing KPIs from the business model, with formula linkage back to source tabs
B26: Build sequence for the analyst
B27: 1. Populate Assumptions - Revenue and Assumptions - Cost for all three scenarios first — every downstream tab reads from these.
B28: 2. Populate Growth - Customers & Merchants with real or benchmarked quarterly acquisition and churn assumptions.
B29: 3. Confirm Transaction Volume Build formulas pull correctly from tab 3 before touching Revenue/Cost Build.
B30: 4. Revenue Build and Cost Build should require no hardcoded numbers — every cell is a formula referencing tabs 1–4.
B31: 5. P&L Summary consolidates 5 and 6. Verify EBITDA breakeven quarter is flagged correctly before presenting.
B32: 6. Scenario Control tab must be wired via INDEX/MATCH into tabs 1–2 before Sensitivity Analysis will produce meaningful ranges.
B33: 7. KPI Dashboard should be built last, once the model is fully linked.
B35: Explicit exclusions
B36: No actual Banglalink subscriber counts, NEO PSP budget figures, or VEON capital allocation amounts are entered anywhere in this workbook. All illustrative values are round placeholder numbers for format demonstration only and are labeled ILLUSTRATIVE in an adjacent cell comment.

Sheet 1. Assumptions - Revenue
A1: Revenue Driver Assumptions (by scenario)
A3: Revenue driver | B3: Conservative | C3: Base | D3: Aggressive | E3: Unit | F3: Source / rationale
A4: Merchant discount rate (MDR) | B4: 0.008 | C4: 0.01 | D4: 0.012 | E4: % of txn value | F4: Bangladesh Bank floor = 1.0% under Bangla QR; range reflects promotional discounting vs. premium tiers
A5: B2B disbursement fee | B5: 0.003 | C5: 0.005 | D5: 0.007 | E5: % of disbursed value | F5: [ANALYST INPUT — benchmark against comparable payroll/vendor disbursement fee structures]
A6: Remittance fee | B6: 0.01 | C6: 0.015 | D6: 0.02 | E6: % of remitted value | F6: [ANALYST INPUT — benchmark against MFS remittance fee precedent]
A7: Gateway / API fee | B7: 0.005 | C7: 0.007 | D7: 0.009 | E7: % of gateway txn value | F7: [ANALYST INPUT — Horizon 2+ revenue line, e-commerce integrations]
A8: Data / referral fee per qualified referral | B8: 50 | C8: 75 | D8: 100 | E8: BDT per referral | F8: [ANALYST INPUT — Horizon 3, dependent on partner bank/NBFI agreements]
A10: ILLUSTRATIVE placeholder values shown — not actual NEO PSP or Banglalink projections. Replace with sourced or benchmarked figures before use.

Sheet 2. Assumptions - Cost
A1: Cost Driver Assumptions (by scenario)
A3: Revenue driver | B3: Conservative | C3: Base | D3: Aggressive | E3: Unit | F3: Source / rationale
A4: Cost per active merchant acquired (CAC) | B4: 900 | C4: 700 | D4: 500 | E4: BDT / merchant | F4: [ANALYST INPUT ; benchmark against comparable PSP/MFS merchant CAC]
A5: Cost per active customer acquired | B5: 40 | C5: 30 | D5: 20 | E5: BDT / customer | F5: Lower than merchant CAC given near-zero-cost Banglalink base channel
A6: Platform / technology cost (Huawei + infra) | B6: 1 | C6: 1 | D6: 1 | E6: Index, Y1=1.0 | F6: [ANALYST INPUT ; per Huawei partnership commercial terms, confidential]
A7: Compliance / licensing cost | B7: 1 | C7: 1 | D7: 1 | E7: Index, Y1=1.0 | F7: AML/CFT, ISMS/PCI, regulatory reporting ; [ANALYST INPUT]
A8: Settlement / NPSB processing fee | B8: 0.001 | C8: 0.0015 | D8: 0.002 | E8: % of txn value | F8: [ANALYST INPUT — confirm against NPSB fee schedule]
A9: Headcount build (FTE, cumulative) | B9: 40 | C9: 65 | D9: 90 | E9: FTE by Y3 | F9: Merchant acquisition, risk/compliance, product ; [ANALYST INPUT]
A11: ILLUSTRATIVE placeholder values shown — not actual NEO PSP or Banglalink cost figures. Items marked [ANALYST INPUT] require sourcing before use.

Sheet 3. Growth - Cust & Merchants
A1: Customer & Merchant Growth Build (quarterly, Y1–Y3)
A3: Quarter | B3: Y1Q1 | C3: Y1Q2 | D3: Y1Q3 | E3: Y1Q4 | F3: Y2Q1 | G3: Y2Q2 | H3: Y2Q3 | I3: Y2Q4 | J3: Y3Q1 | K3: Y3Q2 | L3: Y3Q3 | M3: Y3Q4
A4: Customers
A5: New customers acquired (input) | B5: 8000 | C5: 12000 | D5: 15000 | E5: 15000 | F5: 18000 | G5: 18000 | H5: 20000 | I5: 20000 | J5: 22000 | K5: 22000 | L5: 24000 | M5: 24000
A6: Churn rate (input, % of active base) | B6: 0.03 | C6: 0.03 | D6: 0.03 | E6: 0.03 | F6: 0.03 | G6: 0.03 | H6: 0.03 | I6: 0.03 | J6: 0.03 | K6: 0.03 | L6: 0.03 | M6: 0.03
A7: Active customer base (cumulative) | B7: =B5 -> 8000 | C7: =B7*(1-C6)+C5 -> 19760 | D7: =C7*(1-D6)+D5 -> 34167.2 | E7: =D7*(1-E6)+E5 -> 48142.184 | F7: =E7*(1-F6)+F5 -> 64697.918 | G7: =F7*(1-G6)+G5 -> 80756.981 | H7: =G7*(1-H6)+H5 -> 98334.271 | I7: =H7*(1-I6)+I5 -> 115384.24 | J7: =I7*(1-J6)+J5 -> 133922.72 | ... M7: =L7*(1-M6)+M5 -> 190207.45
A9: Merchants
A10: New merchants acquired (input) | B10: 150 | C10: 220 | D10: 260 | E10: 260 | F10: 300 | G10: 300 | H10: 320 | I10: 320 | J10: 340 | K10: 340 | L10: 360 | M10: 360
A11: Merchant churn rate (input) | B11: 0.02 | C11: 0.02 | D11: 0.02 | E11: 0.02 | F11: 0.02 | G11: 0.02 | H11: 0.02 | I11: 0.02 | J11: 0.02 | K11: 0.02 | L11: 0.02 | M11: 0.02
A12: Active merchant base (cumulative) | B12: =B10 -> 150 | C12: =B12*(1-C11)+C10 -> 367 | D12: =C12*(1-D11)+D10 -> 619.66 | E12: =D12*(1-E11)+E10 -> 867.2668 | F12: =E12*(1-F11)+F10 -> 1149.9215 | G12: =F12*(1-G11)+G10 -> 1426.923 | H12: =G12*(1-H11)+H10 -> 1718.3846 | I12: =H12*(1-I11)+I10 -> 2004.0169 | J12: =I12*(1-J11)+J10 -> 2303.9365 | ... M12: =L12*(1-M11)+M10 -> 3207.7826
A14: ILLUSTRATIVE placeholder acquisition/churn values — replace with real Horizon 1–3 targets from the Growth Framework before use. Row references: active customer base row = 7; active merchant base row = 12.

Sheet 4. Transaction Volume Build
A1: Transaction Volume & Value Build
A3: Quarter | B3: Y1Q1 | C3: Y1Q2 | D3: Y1Q3 | E3: Y1Q4 | F3: Y2Q1 | G3: Y2Q2 | H3: Y2Q3 | I3: Y2Q4 | J3: Y3Q1 | K3: Y3Q2 | L3: Y3Q3 | M3: Y3Q4
A4: Avg. transactions per active customer / qtr (input) | B4: 6 | C4: 6 | D4: 6 | E4: 6 | F4: 6 | G4: 6 | H4: 6 | I4: 6 | J4: 6 | K4: 6 | L4: 6 | M4: 6
A5: Avg. transaction value, BDT (input) | B5: 850 | C5: 850 | D5: 850 | E5: 850 | F5: 850 | G5: 850 | H5: 850 | I5: 850 | J5: 850 | K5: 850 | L5: 850 | M5: 850
A6: Active customer base (link) | B6: ='3. Growth - Cust & Merchants'!B7 -> 8000 | C6: ='3. Growth - Cust & Merchants'!C7 -> 19760 | D6: ='3. Growth - Cust & Merchants'!D7 -> 34167.2 | E6: ='3. Growth - Cust & Merchants'!E7 -> 48142.184 | F6: ='3. Growth - Cust & Merchants'!F7 -> 64697.918 | G6: ='3. Growth - Cust & Merchants'!G7 -> 80756.981 | H6: ='3. Growth - Cust & Merchants'!H7 -> 98334.271 | I6: ='3. Growth - Cust & Merchants'!I7 -> 115384.24 | ... M6: ='3. Growth - Cust & Merchants'!M7 -> 190207.45
A7: Consumer transaction volume (count) | B7: =B6*B4 -> 48000 | C7: =C6*C4 -> 118560 | D7: =D6*D4 -> 205003.2 | E7: =E6*E4 -> 288853.1 | F7: =F6*F4 -> 388187.51 | G7: =G6*G4 -> 484541.89 | H7: =H6*H4 -> 590005.63 | I7: =I6*I4 -> 692305.46 | ... M7: =M6*M4 -> 1141244.7
A8: Consumer transaction value (BDT) | B8: =B7*B5 -> 40800000 | C8: =C7*C5 -> 100776000 | D8: =D7*D5 -> 174252720 | E8: =E7*E5 -> 2.4552514e+08 | F8: =F7*F5 -> 3.2995938e+08 | G8: =G7*G5 -> 4.118606e+08 | H8: =H7*H5 -> 5.0150478e+08 | I8: =I7*I5 -> 5.8845964e+08 | ... M8: =M7*M5 -> 9.7005798e+08
A10: Active merchant base (link) | B10: ='3. Growth - Cust & Merchants'!B12 -> 150 | C10: ='3. Growth - Cust & Merchants'!C12 -> 367 | D10: ='3. Growth - Cust & Merchants'!D12 -> 619.66 | E10: ='3. Growth - Cust & Merchants'!E12 -> 867.2668 | F10: ='3. Growth - Cust & Merchants'!F12 -> 1149.9215 | G10: ='3. Growth - Cust & Merchants'!G12 -> 1426.923 | H10: ='3. Growth - Cust & Merchants'!H12 -> 1718.3846 | I10: ='3. Growth - Cust & Merchants'!I12 -> 2004.0169 | ... M10: ='3. Growth - Cust & Merchants'!M12 -> 3207.7826
A11: Avg. merchant settlement value / qtr, BDT (input) | B11: 180000 | C11: 180000 | D11: 180000 | E11: 180000 | F11: 180000 | G11: 180000 | H11: 180000 | I11: 180000 | J11: 180000 | K11: 180000 | L11: 180000 | M11: 180000
A12: Merchant transaction value (BDT) | B12: =B10*B11 -> 27000000 | C12: =C10*C11 -> 66060000 | D12: =D10*D11 -> 111538800 | E12: =E10*E11 -> 156108024 | F12: =F10*F11 -> 2.0698586e+08 | G12: =G10*G11 -> 2.5684615e+08 | H12: =H10*H11 -> 3.0930922e+08 | I12: =I10*I11 -> 3.6072304e+08 | ... M12: =M10*M11 -> 5.7740088e+08
A14: Consumer transaction value row = 8; merchant transaction value row = 12. These two rows feed the Revenue Build tab.

Sheet 5. Revenue Build
A1: Revenue Build by Stream
A3: Quarter | B3: Y1Q1 | C3: Y1Q2 | D3: Y1Q3 | E3: Y1Q4 | F3: Y2Q1 | G3: Y2Q2 | H3: Y2Q3 | I3: Y2Q4 | J3: Y3Q1 | K3: Y3Q2 | L3: Y3Q3 | M3: Y3Q4
A4: MDR revenue (consumer + merchant txn value × MDR) | B4: =('4. Transaction Volume Build'!B8+'4. Transaction Volume Build'!B12)*'1. Assumptions - Revenue'!$C$4 -> 678000 | C4: =('4. Transaction Volume Build'!C8+'4. Transaction Volume Build'!C12)*'1. Assumptions - Revenue'!$C$4 -> 1668360 | D4: =('4. Transaction Volume Build'!D8+'4. Transaction Volume Build'!D12)*'1. Assumptions - Revenue'!$C$4 -> 2857915.2 | E4: =('4. Transaction Volume Build'!E8+'4. Transaction Volume Build'!E12)*'1. Assumptions - Revenue'!$C$4 -> 4016331.6 | F4: =('4. Transaction Volume Build'!F8+'4. Transaction Volume Build'!F12)*'1. Assumptions - Revenue'!$C$4 -> 5369452.5 | G4: =('4. Transaction Volume Build'!G8+'4. Transaction Volume Build'!G12)*'1. Assumptions - Revenue'!$C$4 -> 6687067.5 | H4: =('4. Transaction Volume Build'!H8+'4. Transaction Volume Build'!H12)*'1. Assumptions - Revenue'!$C$4 -> 8108140.1 | I4: =('4. Transaction Volume Build'!I8+'4. Transaction Volume Build'!I12)*'1. Assumptions - Revenue'!$C$4 -> 9491826.8 | ... M4: =('4. Transaction Volume Build'!M8+'4. Transaction Volume Build'!M12)*'1. Assumptions - Revenue'!$C$4 -> 15474589
A5: B2B disbursement fee revenue | B5: ='4. Transaction Volume Build'!B12*0.3*'1. Assumptions - Revenue'!$C$5 -> 40500 | C5: ='4. Transaction Volume Build'!C12*0.3*'1. Assumptions - Revenue'!$C$5 -> 99090 | D5: ='4. Transaction Volume Build'!D12*0.3*'1. Assumptions - Revenue'!$C$5 -> 167308.2 | E5: ='4. Transaction Volume Build'!E12*0.3*'1. Assumptions - Revenue'!$C$5 -> 234162.04 | F5: ='4. Transaction Volume Build'!F12*0.3*'1. Assumptions - Revenue'!$C$5 -> 310478.8 | G5: ='4. Transaction Volume Build'!G12*0.3*'1. Assumptions - Revenue'!$C$5 -> 385269.22 | H5: ='4. Transaction Volume Build'!H12*0.3*'1. Assumptions - Revenue'!$C$5 -> 463963.83 | I5: ='4. Transaction Volume Build'!I12*0.3*'1. Assumptions - Revenue'!$C$5 -> 541084.56 | ... M5: ='4. Transaction Volume Build'!M12*0.3*'1. Assumptions - Revenue'!$C$5 -> 866101.31
A6: Remittance fee revenue | B6: ='4. Transaction Volume Build'!B8*0.05*'1. Assumptions - Revenue'!$C$6 -> 30600 | C6: ='4. Transaction Volume Build'!C8*0.05*'1. Assumptions - Revenue'!$C$6 -> 75582 | D6: ='4. Transaction Volume Build'!D8*0.05*'1. Assumptions - Revenue'!$C$6 -> 130689.54 | E6: ='4. Transaction Volume Build'!E8*0.05*'1. Assumptions - Revenue'!$C$6 -> 184143.85 | F6: ='4. Transaction Volume Build'!F8*0.05*'1. Assumptions - Revenue'!$C$6 -> 247469.54 | G6: ='4. Transaction Volume Build'!G8*0.05*'1. Assumptions - Revenue'!$C$6 -> 308895.45 | H6: ='4. Transaction Volume Build'!H8*0.05*'1. Assumptions - Revenue'!$C$6 -> 376128.59 | I6: ='4. Transaction Volume Build'!I8*0.05*'1. Assumptions - Revenue'!$C$6 -> 441344.73 | ... M6: ='4. Transaction Volume Build'!M8*0.05*'1. Assumptions - Revenue'!$C$6 -> 727543.48
A7: Gateway / API fee revenue | B7: ='4. Transaction Volume Build'!B12*0.1*'1. Assumptions - Revenue'!$C$7 -> 18900 | C7: ='4. Transaction Volume Build'!C12*0.1*'1. Assumptions - Revenue'!$C$7 -> 46242 | D7: ='4. Transaction Volume Build'!D12*0.1*'1. Assumptions - Revenue'!$C$7 -> 78077.16 | E7: ='4. Transaction Volume Build'!E12*0.1*'1. Assumptions - Revenue'!$C$7 -> 109275.62 | F7: ='4. Transaction Volume Build'!F12*0.1*'1. Assumptions - Revenue'!$C$7 -> 144890.1 | G7: ='4. Transaction Volume Build'!G12*0.1*'1. Assumptions - Revenue'!$C$7 -> 179792.3 | H7: ='4. Transaction Volume Build'!H12*0.1*'1. Assumptions - Revenue'!$C$7 -> 216516.46 | I7: ='4. Transaction Volume Build'!I12*0.1*'1. Assumptions - Revenue'!$C$7 -> 252506.13 | ... M7: ='4. Transaction Volume Build'!M12*0.1*'1. Assumptions - Revenue'!$C$7 -> 404180.61
A8: Total revenue | B8: =SUM(B4:B7) -> 768000 | C8: =SUM(C4:C7) -> 1889274 | D8: =SUM(D4:D7) -> 3233990.1 | E8: =SUM(E4:E7) -> 4543913.1 | F8: =SUM(F4:F7) -> 6072290.9 | G8: =SUM(G4:G7) -> 7561024.5 | H8: =SUM(H4:H7) -> 9164749 | I8: =SUM(I4:I7) -> 10726762 | ... M8: =SUM(M4:M7) -> 17472414
A10: Note: multipliers (0.3, 0.05, 0.1) are placeholder allocation shares of total volume by product line — [ANALYST INPUT: replace with real product-mix assumptions once Horizon 1 data exists]. Total revenue row = 8.

Sheet 6. Cost Build
A1: Cost Build by Category
A3: Quarter | B3: Y1Q1 | C3: Y1Q2 | D3: Y1Q3 | E3: Y1Q4 | F3: Y2Q1 | G3: Y2Q2 | H3: Y2Q3 | I3: Y2Q4 | J3: Y3Q1 | K3: Y3Q2 | L3: Y3Q3 | M3: Y3Q4
A4: Merchant acquisition cost | B4: ='3. Growth - Cust & Merchants'!B10*'2. Assumptions - Cost'!$C$4 -> 105000 | C4: ='3. Growth - Cust & Merchants'!C10*'2. Assumptions - Cost'!$C$4 -> 154000 | D4: ='3. Growth - Cust & Merchants'!D10*'2. Assumptions - Cost'!$C$4 -> 182000 | E4: ='3. Growth - Cust & Merchants'!E10*'2. Assumptions - Cost'!$C$4 -> 182000 | F4: ='3. Growth - Cust & Merchants'!F10*'2. Assumptions - Cost'!$C$4 -> 210000 | G4: ='3. Growth - Cust & Merchants'!G10*'2. Assumptions - Cost'!$C$4 -> 210000 | H4: ='3. Growth - Cust & Merchants'!H10*'2. Assumptions - Cost'!$C$4 -> 224000 | I4: ='3. Growth - Cust & Merchants'!I10*'2. Assumptions - Cost'!$C$4 -> 224000 | ... M4: ='3. Growth - Cust & Merchants'!M10*'2. Assumptions - Cost'!$C$4 -> 252000
A5: Customer acquisition cost | B5: ='3. Growth - Cust & Merchants'!B5*'2. Assumptions - Cost'!$C$5 -> 240000 | C5: ='3. Growth - Cust & Merchants'!C5*'2. Assumptions - Cost'!$C$5 -> 360000 | D5: ='3. Growth - Cust & Merchants'!D5*'2. Assumptions - Cost'!$C$5 -> 450000 | E5: ='3. Growth - Cust & Merchants'!E5*'2. Assumptions - Cost'!$C$5 -> 450000 | F5: ='3. Growth - Cust & Merchants'!F5*'2. Assumptions - Cost'!$C$5 -> 540000 | G5: ='3. Growth - Cust & Merchants'!G5*'2. Assumptions - Cost'!$C$5 -> 540000 | H5: ='3. Growth - Cust & Merchants'!H5*'2. Assumptions - Cost'!$C$5 -> 600000 | I5: ='3. Growth - Cust & Merchants'!I5*'2. Assumptions - Cost'!$C$5 -> 600000 | ... M5: ='3. Growth - Cust & Merchants'!M5*'2. Assumptions - Cost'!$C$5 -> 720000
A6: Platform / technology cost (input index × base, BDT) | B6: 5000000 | C6: 5000000 | D6: 5000000 | E6: 5000000 | F6: 5000000 | G6: 5000000 | H6: 5000000 | I6: 5000000 | J6: 5000000 | K6: 5000000 | L6: 5000000 | M6: 5000000
A7: Compliance / licensing cost (input, BDT) | B7: 2000000 | C7: 2000000 | D7: 2000000 | E7: 2000000 | F7: 2000000 | G7: 2000000 | H7: 2000000 | I7: 2000000 | J7: 2000000 | K7: 2000000 | L7: 2000000 | M7: 2000000
A8: Settlement / processing cost | B8: =('4. Transaction Volume Build'!B8+'4. Transaction Volume Build'!B12)*'2. Assumptions - Cost'!$C$8 -> 101700 | C8: =('4. Transaction Volume Build'!C8+'4. Transaction Volume Build'!C12)*'2. Assumptions - Cost'!$C$8 -> 250254 | D8: =('4. Transaction Volume Build'!D8+'4. Transaction Volume Build'!D12)*'2. Assumptions - Cost'!$C$8 -> 428687.28 | E8: =('4. Transaction Volume Build'!E8+'4. Transaction Volume Build'!E12)*'2. Assumptions - Cost'!$C$8 -> 602449.74 | F8: =('4. Transaction Volume Build'!F8+'4. Transaction Volume Build'!F12)*'2. Assumptions - Cost'!$C$8 -> 805417.87 | G8: =('4. Transaction Volume Build'!G8+'4. Transaction Volume Build'!G12)*'2. Assumptions - Cost'!$C$8 -> 1003060.1 | H8: =('4. Transaction Volume Build'!H8+'4. Transaction Volume Build'!H12)*'2. Assumptions - Cost'!$C$8 -> 1216221 | I8: =('4. Transaction Volume Build'!I8+'4. Transaction Volume Build'!I12)*'2. Assumptions - Cost'!$C$8 -> 1423774 | ... M8: =('4. Transaction Volume Build'!M8+'4. Transaction Volume Build'!M12)*'2. Assumptions - Cost'!$C$8 -> 2321188.3
A9: Headcount / people cost (input, BDT) | B9: 8000000 | C9: 8000000 | D9: 8000000 | E9: 8000000 | F9: 8000000 | G9: 8000000 | H9: 8000000 | I9: 8000000 | J9: 8000000 | K9: 8000000 | L9: 8000000 | M9: 8000000
A10: Total cost | B10: =SUM(B4:B9) -> 15446700 | C10: =SUM(C4:C9) -> 15764254 | D10: =SUM(D4:D9) -> 16060687 | E10: =SUM(E4:E9) -> 16234450 | F10: =SUM(F4:F9) -> 16555418 | G10: =SUM(G4:G9) -> 16753060 | H10: =SUM(H4:H9) -> 17040221 | I10: =SUM(I4:I9) -> 17247774 | ... M10: =SUM(M4:M9) -> 18293188
A12: Platform, compliance, and headcount costs are entered as direct BDT inputs (not derivable from public data) — [ANALYST INPUT]. Total cost row = 10.

Sheet 7. P&L Summary
A1: P&L Summary (Annualized, Y1–Y3)
B3: Year 1 | C3: Year 2 | D3: Year 3
A4: Total revenue | B4: =SUM('5. Revenue Build'!B8:E8) -> 10435177 | C4: =SUM('5. Revenue Build'!F8:I8) -> 33524827 | D4: =SUM('5. Revenue Build'!J8:M8) -> 59682766
A5: Total cost | B5: =SUM('6. Cost Build'!B10:E10) -> 63506091 | C5: =SUM('6. Cost Build'!F10:I10) -> 67596473 | D5: =SUM('6. Cost Build'!J10:M10) -> 71666660
A6: EBITDA | B6: =B4-B5 -> -53070914 | C6: =C4-C5 -> -34071646 | D6: =D4-D5 -> -11983893
A7: EBITDA margin | B7: =B6/B4 -> -5.0857702 | C7: =C6/C4 -> -1.0163109 | D7: =D6/D4 -> -0.20079319
A9: Cumulative EBITDA (for payback) | B9: =B6 -> -53070914 | C9: =B9+C6 -> -87142560 | D9: =C9+D6 -> -99126453
A11: Breakeven flag (EBITDA-positive year) | B11: =IF(B6>0,"Y1",IF(C6>0,"Y2",IF(D6>0,"Y3","Beyond Y3"))) -> Beyond Y3
A13: NPV/IRR and payback period should be computed here once monthly (not annualized) cash flows and a discount rate assumption are added — [ANALYST INPUT: WACC/discount rate].

Sheet 8. Scenario Control
A1: Scenario Control
A3: Active scenario | B3: Base
A5: Wiring instructions: replace the hardcoded '$C$4' / '$C$5' style references in Revenue Build and Cost Build with =INDEX(range, MATCH($B$3,{"Conservative","Base","Aggressive"},0)) once this control is finalized, so every downstream tab responds to a single scenario toggle here.

Sheet 9. Sensitivity Analysis
A1: Sensitivity Analysis — Year 3 EBITDA
A3: Two-variable grid: rows = merchant acquisition pace (% of Base), columns = MDR (bps)
A5: Merchant pace \ MDR (bps) | B5: 80 | C5: 90 | D5: 100 | E5: 110 | F5: 120
A6: 70% | B6: [LINK TO Y3 EBITDA] | C6: [LINK TO Y3 EBITDA] | D6: [LINK TO Y3 EBITDA] | E6: [LINK TO Y3 EBITDA] | F6: [LINK TO Y3 EBITDA]
A7: 85% | B7: [LINK TO Y3 EBITDA] | C7: [LINK TO Y3 EBITDA] | D7: [LINK TO Y3 EBITDA] | E7: [LINK TO Y3 EBITDA] | F7: [LINK TO Y3 EBITDA]
A8: 100% (Base) | B8: [LINK TO Y3 EBITDA] | C8: [LINK TO Y3 EBITDA] | D8: [LINK TO Y3 EBITDA] | E8: [LINK TO Y3 EBITDA] | F8: [LINK TO Y3 EBITDA]
A9: 115% | B9: [LINK TO Y3 EBITDA] | C9: [LINK TO Y3 EBITDA] | D9: [LINK TO Y3 EBITDA] | E9: [LINK TO Y3 EBITDA] | F9: [LINK TO Y3 EBITDA]
A10: 130% | B10: [LINK TO Y3 EBITDA] | C10: [LINK TO Y3 EBITDA] | D10: [LINK TO Y3 EBITDA] | E10: [LINK TO Y3 EBITDA] | F10: [LINK TO Y3 EBITDA]
A12: Each cell should be built as a formula referencing a duplicated Growth/Revenue Build calculation with the row's merchant-pace multiplier and column's MDR applied — or, for analysts comfortable with it, an Excel What-If Data Table referencing '7. P&L Summary'!D6 as the formula cell (top-left corner), with merchant pace and MDR as row/column input cells. Avoid relying on Excel's native Data Table feature if this file may be opened in non-Excel tools — explicit formulas are more portable.

Sheet 10. KPI Dashboard
A1: KPI Dashboard — Governing Metrics
A3: KPI | B3: Year 1 | C3: Year 2 | D3: Year 3
A4: Active merchant count (Y-end) | B4: ='3. Growth - Cust & Merchants'!E12 -> 867.2668 | C4: ='3. Growth - Cust & Merchants'!I12 -> 2004.0169 | D4: ='3. Growth - Cust & Merchants'!M12 -> 3207.7826
A5: Active customer count (Y-end) | B5: ='3. Growth - Cust & Merchants'!E7 -> 48142.184 | C5: ='3. Growth - Cust & Merchants'!I7 -> 115384.24 | D5: ='3. Growth - Cust & Merchants'!M7 -> 190207.45
A6: Cost per active merchant acquired | B6: [LINK / ANALYST INPUT] | C6: [LINK / ANALYST INPUT] | D6: [LINK / ANALYST INPUT]
A7: Transaction volume per active merchant | B7: [LINK / ANALYST INPUT] | C7: [LINK / ANALYST INPUT] | D7: [LINK / ANALYST INPUT]
A8: Settlement reliability / uptime (%) | B8: [LINK / ANALYST INPUT] | C8: [LINK / ANALYST INPUT] | D8: [LINK / ANALYST INPUT]
A9: EBITDA margin | B9: [LINK / ANALYST INPUT] | C9: [LINK / ANALYST INPUT] | D9: [LINK / ANALYST INPUT]
A11: Settlement reliability/uptime is an operational metric, not derivable from this financial model — source from platform monitoring once live. This dashboard tab should mirror the standalone KPI Dashboard deliverable.
