Workbook

Sheet Model Notes
A1: Roar Regiment — Financial Model (Rebuilt)
A3: This workbook replaces the original Roar Regiment financial projection. The original file contained two unreconciled sets of numbers — the Revenue Breakdown/Operating Cost tabs used one dataset (BDT 32.5M initial investment, BDT 35–64M revenue range) while the Key Metrics tab computed NPV/IRR/Payback off an entirely different, unexplained dataset (BDT 200M investment, BDT 120–240M revenue range). That inconsistency is the single biggest credibility risk a reviewer would find, so fixing it was the priority for this rebuild.
A7: STRUCTURE: every figure in this workbook traces back to the Assumptions tab. Operating Costs, Revenue Model, Funding Mix, and Key Metrics all use formulas that reference Assumptions or one another — there is exactly one place to change a growth rate or a cost line, and it flows through the whole model. Initial Investment is built up from a cost breakdown, not asserted as a round number.
A11: REPOSITIONING LOGIC: consistent with the Strategic Repositioning Brief, this model assumes (1) a leaner cost base than the original 4-roster, gaming-house concept, (2) revenue distributed through Banglalink's own Toffee (content/media rights), MyBL (merchandise/loyalty), and Ryze (youth brand) platforms rather than a standalone media operation, and (3) a hybrid funding structure where Banglalink covers the majority of costs in Year 1 and the funding burden shifts toward sponsorship/media-rights revenue over time.
A15: HONEST FINDING — read before presenting this model: under the Most Likely case, the venture does NOT reach standalone breakeven within the 5-year horizon. Banglalink's funding requirement narrows from roughly 72% of opex in Year 1 to roughly 26% of opex in Year 5, but the venture remains cash-flow negative throughout. This is disclosed deliberately rather than smoothed over — a reviewer testing the model's assumptions would find this quickly, and it is also a realistic pattern: Toffee itself took from 2020 launch to FY2025 to reach material ad-revenue scale. The Key Metrics tab treats this as a strategic/ecosystem investment with a bounded, declining funding requirement — not as a standalone NPV-positive project — and shows Pessimistic/Optimistic scenarios alongside the Most Likely case so the range is visible rather than hidden behind one number.
A19: WHAT IS STILL AN ASSUMPTION, NOT A FACT: sponsorship and media-rights growth rates (45%/yr and 50%/yr respectively) are illustrative, not sourced to specific signed deals — there are none. They are calibrated to be aggressive-but-plausible off a small base, similar in spirit to Toffee's own reported 63% YoY ad-revenue growth. Treat these as the primary lever to stress-test if this model is challenged in an interview setting.
A23: SOURCES USED: VEON Integrated Annual Report 2025 (Bangladesh/Banglalink section) for the BDT/USD FX rate, Toffee/MyBL/Ryze user and revenue metrics, and Banglalink's disclosed strategic priorities. Where no external source exists (e.g., specific cost line items, sponsorship deal sizes), the assumption is labeled as an internal estimate in the Notes column of the relevant tab.

Sheet Assumptions
A1: Assumptions — Single Source of Truth (Most Likely Case)
A3: Metric | B3: Value | C3: Unit | D3: Source / Rationale
A4: GENERAL
A5: Initial Investment (Banglalink Seed) | B5: ='Initial Investment'!B12 -> 28080000 | C5: BDT | D5: Linked from Initial Investment tab (built up from cost breakdown)
A6: Discount Rate (illustrative) | B6: 0.12 | C6: % | D6: Illustrative emerging-market digital-venture discount rate; not Banglalink's actual disclosed WACC
A7: BDT / USD Exchange Rate | B7: 121.7 | C7: BDT per USD | D7: Source: VEON Integrated Annual Report 2025, FY2025 average rate
A9: COST GROWTH RATES (per annum)
A10: Player Salaries & Coaching | B10: 0.08 | C10: %/yr | D10: Lean, mostly-stable headcount; inflation-level increases
A11: Content Production (Toffee distribution) | B11: 0.12 | C11: %/yr | D11: Scales with content slate as audience grows
A12: Marketing & Fan Engagement (Ryze/MyBL) | B12: 0.1 | C12: %/yr | D12: Internal estimate
A13: Platform & Tech Integration | B13: 0.06 | C13: %/yr | D13: Mostly fixed integration cost — asset-light logic
A14: Travel & Tournament Participation | B14: 0.1 | C14: %/yr | D14: Internal estimate
A15: Merchandise COGS (% of merch revenue) | B15: 0.4 | C15: % | D15: Industry-typical apparel/merch COGS ratio
A16: Contingency (% of subtotal opex) | B16: 0.05 | C16: % | D16: Standard contingency buffer
A18: REVENUE GROWTH RATES (per annum)
A19: Sponsorship | B19: 0.45 | C19: %/yr | D19: Illustrative — no signed deals exist; aggressive-but-plausible off small base
A20: Media Rights (Toffee content revenue share) | B20: 0.5 | C20: %/yr | D20: Calibrated near Toffee's own reported 63% YoY ad-revenue growth (FY2025)
A21: Merch Fanbase Growth | B21: 0.2 | C21: %/yr | D21: Benchmarked near Banglalink Multiplay adoption growth (23.6% YoY, FY2025)
A22: Academy / Fan Engagement | B22: 0.25 | C22: %/yr | D22: Internal estimate
A23: Prize Money & Content Monetization | B23: 0.1 | C23: %/yr | D23: Deliberately modest — not a strategic revenue driver
A25: MERCHANDISE ASSUMPTIONS
A26: Year 1 Fanbase (merch-eligible) | B26: 40000 | C26: people | D26: Deliberately conservative vs. original file's unsupported 100,000
A27: Conversion Rate (fans to buyers) | B27: 0.03 | C27: % | D27: Industry-typical range, retained from original file
A28: AOV per Buyer (BDT/year) | B28: 800 | C28: BDT | D28: Retained near original file's assumption, held flat across years (conservative)
A30: SCENARIO SENSITIVITY MULTIPLIERS (applied to blended 5-yr CAGR — see Key Metrics)
A31: Pessimistic — Revenue Growth Multiplier | B31: 0.6 | C31: x | D31: Slower sponsor/media-rights uptake
A32: Pessimistic — Opex Growth Multiplier | B32: 1.15 | C32: x | D32: Cost overruns / slower efficiency gains
A33: Optimistic — Revenue Growth Multiplier | B33: 1.4 | C33: x | D33: Faster sponsor/media-rights uptake
A34: Optimistic — Opex Growth Multiplier | B34: 0.9 | C34: x | D34: Faster efficiency gains from platform integration

Sheet Initial Investment
A1: Initial Investment — Banglalink Seed Capital
A3: Cost Head | B3: Amount (BDT) | C3: Notes
A4: Content Production & Broadcast Setup (Toffee integration) | B4: 6000000 | C4: Cameras, editing, streaming setup to plug into Toffee's content pipeline
A5: Player / Roster Signing & Launch Salary Buffer | B5: 5000000 | C5: Covers first-quarter salaries ahead of revenue ramp
A6: Academy Setup (trials, coaching infrastructure) | B6: 4000000 | C6: Lean academy — not a full gaming house
A7: Brand Integration & Launch Marketing (Ryze / MyBL) | B7: 5000000 | C7: Co-branded launch campaign through existing apps
A8: Merchandise & E-Store Setup (MyBL commerce integration) | B8: 2000000 | C8: Uses MyBL's existing commerce rails, not a bespoke store
A9: Platform & Tech Integration (Toffee/MyBL API, loyalty system) | B9: 4000000 | C9: One-time integration cost — internal estimate
A10: Subtotal | B10: =SUM(B4:B9) -> 26000000
A11: Contingency (8% of subtotal) | B11: =B10*0.08 -> 2080000 | C11: Standard contingency for a launch-stage capital budget
A12: TOTAL INITIAL INVESTMENT | B12: =B10+B11 -> 28080000
A14: USD equivalent at FY2025 average rate: | B14: =B12/Assumptions!$B$7 -> 230731.31

Sheet Revenue Model
A1: Revenue Model — Years 1 to 5 (Most Likely Case)
A3: Revenue Stream | B3: Year 1 | C3: Year 2 | D3: Year 3 | E3: Year 4 | F3: Year 5 | G3: Notes
A4: Sponsorship (Banglalink anchor + brand partners) | B4: 4000000 | C4: =B4*(1+Assumptions!$B$19) -> 5800000 | D4: =C4*(1+Assumptions!$B$19) -> 8410000 | E4: =D4*(1+Assumptions!$B$19) -> 12194500 | F4: =E4*(1+Assumptions!$B$19) -> 17682025 | G4: Illustrative — see Model Notes. No signed sponsorship deals exist.
A5: Media Rights (Toffee content revenue share) | B5: 1000000 | C5: =B5*(1+Assumptions!$B$20) -> 1500000 | D5: =C5*(1+Assumptions!$B$20) -> 2250000 | E5: =D5*(1+Assumptions!$B$20) -> 3375000 | F5: =E5*(1+Assumptions!$B$20) -> 5062500 | G5: Content licensed to Toffee's ad-supported slate; growth rate near Toffee's own FY2025 ad-revenue growth
A7: Merchandise (transacted via MyBL)
A8: Fanbase (merch-eligible) | B8: =Assumptions!$B$26 -> 40000 | C8: =B8*(1+Assumptions!$B$21) -> 48000 | D8: =C8*(1+Assumptions!$B$21) -> 57600 | E8: =D8*(1+Assumptions!$B$21) -> 69120 | F8: =E8*(1+Assumptions!$B$21) -> 82944
A9: Conversion Rate | B9: =Assumptions!$B$27 -> 0.03 | C9: =Assumptions!$B$27 -> 0.03 | D9: =Assumptions!$B$27 -> 0.03 | E9: =Assumptions!$B$27 -> 0.03 | F9: =Assumptions!$B$27 -> 0.03
A10: AOV per Buyer (BDT/yr) | B10: =Assumptions!$B$28 -> 800 | C10: =Assumptions!$B$28 -> 800 | D10: =Assumptions!$B$28 -> 800 | E10: =Assumptions!$B$28 -> 800 | F10: =Assumptions!$B$28 -> 800
A11: Merchandise Revenue | B11: =B8*B9*B10 -> 960000 | C11: =C8*C9*C10 -> 1152000 | D11: =D8*D9*D10 -> 1382400 | E11: =E8*E9*E10 -> 1658880 | F11: =F8*F9*F10 -> 1990656
A13: Academy / Fan Engagement (fees, ticketed events) | B13: 1000000 | C13: =B13*(1+Assumptions!$B$22) -> 1250000 | D13: =C13*(1+Assumptions!$B$22) -> 1562500 | E13: =D13*(1+Assumptions!$B$22) -> 1953125 | F13: =E13*(1+Assumptions!$B$22) -> 2441406.2
A14: Prize Money & Content Monetization | B14: 500000 | C14: =B14*(1+Assumptions!$B$23) -> 550000 | D14: =C14*(1+Assumptions!$B$23) -> 605000 | E14: =D14*(1+Assumptions!$B$23) -> 665500 | F14: =E14*(1+Assumptions!$B$23) -> 732050 | G14: Deliberately modest — prize winnings are not a strategic driver of this venture
A16: TOTAL REVENUE | B16: =B4+B5+B11+B13+B14 -> 7460000 | C16: =C4+C5+C11+C13+C14 -> 10252000 | D16: =D4+D5+D11+D13+D14 -> 14209900 | E16: =E4+E5+E11+E13+E14 -> 19847005 | F16: =F4+F5+F11+F13+F14 -> 27908637

Sheet Operating Costs
A1: Operating Costs — Years 1 to 5 (Most Likely Case)
A3: Cost Item | B3: Year 1 | C3: Year 2 | D3: Year 3 | E3: Year 4 | F3: Year 5 | G3: Notes
A4: Player Salaries & Coaching (lean roster + academy) | B4: 14000000 | C4: =B4*(1+Assumptions!$B$10) -> 15120000 | D4: =C4*(1+Assumptions!$B$10) -> 16329600 | E4: =D4*(1+Assumptions!$B$10) -> 17635968 | F4: =E4*(1+Assumptions!$B$10) -> 19046845 | G4: 2–3 competitive titles, not 4 — see Repositioning Brief
A5: Content Production (for Toffee distribution) | B5: 4000000 | C5: =B5*(1+Assumptions!$B$11) -> 4480000 | D5: =C5*(1+Assumptions!$B$11) -> 5017600 | E5: =D5*(1+Assumptions!$B$11) -> 5619712 | F5: =E5*(1+Assumptions!$B$11) -> 6294077.4
A6: Marketing & Fan Engagement (Ryze / MyBL channels) | B6: 3000000 | C6: =B6*(1+Assumptions!$B$12) -> 3300000 | D6: =C6*(1+Assumptions!$B$12) -> 3630000 | E6: =D6*(1+Assumptions!$B$12) -> 3993000 | F6: =E6*(1+Assumptions!$B$12) -> 4392300
A7: Platform & Tech Integration / Maintenance | B7: 1500000 | C7: =B7*(1+Assumptions!$B$13) -> 1590000 | D7: =C7*(1+Assumptions!$B$13) -> 1685400 | E7: =D7*(1+Assumptions!$B$13) -> 1786524 | F7: =E7*(1+Assumptions!$B$13) -> 1893715.4 | G7: Low marginal growth — reuses Toffee/MyBL infrastructure (asset-light logic)
A8: Travel & Tournament Participation | B8: 2500000 | C8: =B8*(1+Assumptions!$B$14) -> 2750000 | D8: =C8*(1+Assumptions!$B$14) -> 3025000 | E8: =D8*(1+Assumptions!$B$14) -> 3327500 | F8: =E8*(1+Assumptions!$B$14) -> 3660250
A9: Subtotal (Core Opex) | B9: =SUM(B4:B8) -> 25000000 | C9: =SUM(C4:C8) -> 27240000 | D9: =SUM(D4:D8) -> 29687600 | E9: =SUM(E4:E8) -> 32362704 | F9: =SUM(F4:F8) -> 35287188
A10: Merchandise COGS | B10: ='Revenue Model'!B11*Assumptions!$B$15 -> 384000 | C10: ='Revenue Model'!C11*Assumptions!$B$15 -> 460800 | D10: ='Revenue Model'!D11*Assumptions!$B$15 -> 552960 | E10: ='Revenue Model'!E11*Assumptions!$B$15 -> 663552 | F10: ='Revenue Model'!F11*Assumptions!$B$15 -> 796262.4 | G10: Equals Merchandise Revenue (Revenue Model tab) × COGS % (Assumptions tab)
A11: Contingency | B11: =(B9+B10)*Assumptions!$B$16 -> 1269200 | C11: =(C9+C10)*Assumptions!$B$16 -> 1385040 | D11: =(D9+D10)*Assumptions!$B$16 -> 1512028 | E11: =(E9+E10)*Assumptions!$B$16 -> 1651312.8 | F11: =(F9+F10)*Assumptions!$B$16 -> 1804172.5
A12: TOTAL OPERATING COSTS | B12: =B9+B10+B11 -> 26653200 | C12: =C9+C10+C11 -> 29085840 | D12: =D9+D10+D11 -> 31752588 | E12: =E9+E10+E11 -> 34677569 | F12: =F9+F10+F11 -> 37887623

Sheet Funding Mix
A1: Funding Mix — Hybrid Model (Banglalink Seed → Sponsor/Media-Rights Funded)
A3: Metric | B3: Year 1 | C3: Year 2 | D3: Year 3 | E3: Year 4 | F3: Year 5 | G3: Notes
A4: Total Revenue | B4: ='Revenue Model'!B16 -> 7460000 | C4: ='Revenue Model'!C16 -> 10252000 | D4: ='Revenue Model'!D16 -> 14209900 | E4: ='Revenue Model'!E16 -> 19847005 | F4: ='Revenue Model'!F16 -> 27908637
A5: Total Operating Costs | B5: ='Operating Costs'!B12 -> 26653200 | C5: ='Operating Costs'!C12 -> 29085840 | D5: ='Operating Costs'!D12 -> 31752588 | E5: ='Operating Costs'!E12 -> 34677569 | F5: ='Operating Costs'!F12 -> 37887623
A6: Net Venture Cash Flow (Revenue − Opex) | B6: =B4-B5 -> -19193200 | C6: =C4-C5 -> -18833840 | D6: =D4-D5 -> -17542688 | E6: =E4-E5 -> -14830564 | F6: =F4-F5 -> -9978986
A7: Banglalink Funding Requirement | B7: =MAX(B5-B4,0) -> 19193200 | C7: =MAX(C5-C4,0) -> 18833840 | D7: =MAX(D5-D4,0) -> 17542688 | E7: =MAX(E5-E4,0) -> 14830564 | F7: =MAX(F5-F4,0) -> 9978986
A8: Revenue-Funded Share of Opex | B8: =B4/B5 -> 0.27989135 | C8: =C4/C5 -> 0.35247392 | D8: =D4/D5 -> 0.44751943 | E8: =E4/E5 -> 0.57232977 | F8: =F4/F5 -> 0.7366162
A9: Banglalink-Funded Share of Opex | B9: =1-B8 -> 0.72010865 | C9: =1-C8 -> 0.64752608 | D9: =1-D8 -> 0.55248057 | E9: =1-E8 -> 0.42767023 | F9: =1-F8 -> 0.2633838
A11: Reading this table: Year 1 shows Banglalink funding roughly three-quarters of operating costs, consistent with a seed-funded launch. That share should decline each year as sponsorship and Toffee media-rights revenue scale. See Key Metrics tab for whether this reaches the “majority third-party funded” threshold described in the Strategic Repositioning Brief, and by when.

Sheet Key Metrics
A1: Key Metrics — NPV, IRR, Payback, ROI, and Scenario Sensitivity
A3: Metric | B3: Year 0 | C3: Year 1 | D3: Year 2 | E3: Year 3 | F3: Year 4 | G3: Year 5
A4: Net Cash Flow (Banglalink perspective) | B4: =-Assumptions!$B$5 -> -28080000 | C4: ='Funding Mix'!B6 -> -19193200 | D4: ='Funding Mix'!C6 -> -18833840 | E4: ='Funding Mix'!D6 -> -17542688 | F4: ='Funding Mix'!E6 -> -14830564 | G4: ='Funding Mix'!F6 -> -9978986
A5: Cumulative Net Cash Flow | B5: =B4 -> -28080000 | C5: =B5+C4 -> -47273200 | D5: =C5+D4 -> -66107040 | E5: =D5+E4 -> -83649728 | F5: =E5+F4 -> -98480292 | G5: =F5+G4 -> -1.0845928e+08
A7: NPV (at Assumptions discount rate) | B7: =NPV(Assumptions!$B$6,C4:G4)+B4 -> -87804983
A8: IRR (5-year horizon) | B8: =IFERROR(IRR(B4:G4,-0.5),"Not computable — cash flows stay negative") -> Not computable — cash flows stay negative
A9: Breakeven achieved within 5 years? | B9: =IF(G5>=0,"Yes","No — funding requirement persists beyond Year 5") -> No — funding requirement persists beyond Year 5
A10: 5-Year Return on Initial Investment | B10: =G5/-B4 -> -3.8625099
A12: Most Likely case reads negative on NPV/ROI and “not computable” on IRR because cash flows do not cross zero within 5 years. That is the honest output of this model, not an error — see Model Notes. The metric that matters here is the Funding Intensity trend below: is Banglalink's exposure shrinking and bounded, or open-ended?
A14: FUNDING INTENSITY TREND (Banglalink-Funded Share of Opex, linked from Funding Mix)
A15: Banglalink-Funded Share of Opex | C15: ='Funding Mix'!B9 -> 0.72010865 | D15: ='Funding Mix'!C9 -> 0.64752608 | E15: ='Funding Mix'!D9 -> 0.55248057 | F15: ='Funding Mix'!E9 -> 0.42767023 | G15: ='Funding Mix'!F9 -> 0.2633838
A17: Interpretation: the Most Likely case does not reach full third-party funding within the plan horizon, but the trend is consistently downward — Banglalink's exposure per year shrinks even though the venture has not fully broken even. That is a materially more defensible claim than the original file's flat, unexplained sponsorship assumption.
A20: SCENARIO SENSITIVITY (blended CAGR method — see Model Notes for methodology)
A22: Revenue CAGR, Year 1→Year 5 (Most Likely, implied) | B22: =('Revenue Model'!F16/'Revenue Model'!B16)^(1/4)-1 -> 0.39075283
A23: Opex CAGR, Year 1→Year 5 (Most Likely, implied) | B23: =('Operating Costs'!F12/'Operating Costs'!B12)^(1/4)-1 -> 0.091910396
A25: Pessimistic (Rev x Scenario
A26: Revenue (extrapolated) | C26: ='Revenue Model'!B16 -> 7460000 | D26: =$C$26*(1+B22*Assumptions!$B$31)^1 -> 9209009.6 | E26: =$C$26*(1+B22*Assumptions!$B$31)^2 -> 11368078 | F26: =$C$26*(1+B22*Assumptions!$B$31)^3 -> 14033343 | G26: =$C$26*(1+B22*Assumptions!$B$31)^4 -> 17323484
A27: Opex (extrapolated) | C27: ='Operating Costs'!B12 -> 26653200 | D27: =$C$27*(1+B23*Assumptions!$B$32)^1 -> 29470362 | E27: =$C$27*(1+B23*Assumptions!$B$32)^2 -> 32585290 | F27: =$C$27*(1+B23*Assumptions!$B$32)^3 -> 36029456 | G27: =$C$27*(1+B23*Assumptions!$B$32)^4 -> 39837659
A28: Net Cash Flow | B28: =-Assumptions!$B$5 -> -28080000 | C28: =C26-C27 -> -19193200 | D28: =D26-D27 -> -20261352 | E28: =E26-E27 -> -21217212 | F28: =F26-F27 -> -21996113 | G28: =G26-G27 -> -22514176
A29: Cumulative Net Cash Flow | B29: =B28 -> -28080000 | C29: =B29+C28 -> -47273200 | D29: =C29+D28 -> -67534552 | E29: =D29+E28 -> -88751765 | F29: =E29+F28 -> -1.1074788e+08 | G29: =F29+G28 -> -1.3326205e+08
A31: Optimistic Scenario
A32: Revenue (extrapolated) | C32: ='Revenue Model'!B16 -> 7460000 | D32: =$C$32*(1+B22*Assumptions!$B$33)^1 -> 11541023 | E32: =$C$32*(1+B22*Assumptions!$B$33)^2 -> 17854585 | F32: =$C$32*(1+B22*Assumptions!$B$33)^3 -> 27622006 | G32: =$C$32*(1+B22*Assumptions!$B$33)^4 -> 42732733
A33: Opex (extrapolated) | C33: ='Operating Costs'!B12 -> 26653200 | D33: =$C$33*(1+B23*Assumptions!$B$34)^1 -> 28857936 | E33: =$C$33*(1+B23*Assumptions!$B$34)^2 -> 31245045 | F33: =$C$33*(1+B23*Assumptions!$B$34)^3 -> 33829615 | G33: =$C$33*(1+B23*Assumptions!$B$34)^4 -> 36627980
A34: Net Cash Flow | B34: =-Assumptions!$B$5 -> -28080000 | C34: =C32-C33 -> -19193200 | D34: =D32-D33 -> -17316913 | E34: =E32-E33 -> -13390461 | F34: =F32-F33 -> -6207609.9 | G34: =G32-G33 -> 6104753.5
A35: Cumulative Net Cash Flow | B35: =B34 -> -28080000 | C35: =B35+C34 -> -47273200 | D35: =C35+D34 -> -64590113 | E35: =D35+E34 -> -77980574 | F35: =E35+F34 -> -84188184 | G35: =F35+G34 -> -78083430
A38: SCENARIO SUMMARY
A39: Scenario | B39: Cumulative Net CF, Year 5 | C39: IRR (5-yr) | D39: NPV | E39: IRR Computable?
A40: Most Likely | B40: =G5 -> -1.0845928e+08 | C40: =B8 -> Not computable — cash flows stay negative | D40: =B7 -> -87804983 | E40: =IF(ISNUMBER(C40),"Yes","No") -> No
A41: Pessimistic | B41: =G29 -> -1.3326205e+08 | C41: =IFERROR(IRR(B28:G28,-0.5),"n.a.") -> n.a. | D41: =NPV(Assumptions!$B$6,C28:G28)+B28 -> -1.0322508e+08 | E41: =IF(ISNUMBER(C41),"Yes","No") -> No
A42: Optimistic | B42: =G35 -> -78083430 | C42: =IFERROR(IRR(B34:G34,-0.5),"n.a.") -> -0.61240728 | D42: =NPV(Assumptions!$B$6,C34:G34)+B34 -> -69033836 | E42: =IF(ISNUMBER(C42),"Yes","No") -> Yes
A44: Note on IRR “n.a.” results: Pessimistic never turns cash-flow positive, so IRR is genuinely undefined. Optimistic turns positive only in Year 5 by a small margin after four deeply negative years — IRR is mathematically defined there (≈ –61%, i.e. still a poor return) but standard iterative solvers, including Excel's, frequently fail to converge on that shape of cash flow. NPV and Cumulative Net Cash Flow are the more reliable reads for this venture profile.
