Workbook
Name Assum_TaxRate: Assumptions!$B$21
Name Assum_TermGrowth: Assumptions!$B$38
Name Assum_WACC: Assumptions!$B$36
Name Comps_EVEBITDA_Median: 'Trading Comparables'!$H$14
Name Comps_EVSales_Median: 'Trading Comparables'!$I$14
Name Cover_ReportDate: Cover!$E$17
Name Cover_Version: Cover!$F$20
Name DCF_EquityValue: 'DCF Valuation'!$B$16
Name DCF_EV: 'DCF Valuation'!$B$13
Name DCF_ImpliedPrice: 'DCF Valuation'!$B$18
Name Fcst_Digital_Pct: 'Revenue Forecast'!B16:G16
Name Fcst_EBITDA: 'Operating Forecast'!B12:G12
Name Fcst_Revenue_Total: 'Revenue Forecast'!B9:G9
Name Fcst_UFCF: 'Operating Forecast'!C21:G21
Name Hist_EBITDA: 'Historical Financial Statements'!B7:F7
Name Hist_FCF: 'Historical Financial Statements'!B15:F15
Name Hist_NetDebt: 'Historical Financial Statements'!B19:F19
Name Hist_Revenue: 'Historical Financial Statements'!B5:F5
Name Raw_EBITDA_Total: 'Raw Financial Data'!C11:G11
Name Raw_NetDebt: 'Raw Financial Data'!C16:G16
Name Raw_Revenue_Total: 'Raw Financial Data'!C9:G9
Name Sens_TermGrowth_Range: 'Sensitivity Analysis'!B4:F4
Name Sens_WACC_Range: 'Sensitivity Analysis'!A5:A9
Name Summary_Rating: 'Investment Summary'!$B$3
Name Summary_TargetPrice: 'Investment Summary'!$B$4

Sheet Cover
A2: VEON LTD. — INSTITUTIONAL VALUATION WORKBOOK
A6: VEON Ltd. (NASDAQ: VEON)
A8: Frontier-Market Digital Operator — Telecommunications Sector
A11: Full-Year DCF, Trading Comparables & Sensitivity Model
B15: Prepared By | E15: S M Zawadul Huq
B16: Specialization | E16: Corporate Finance, Strategy & Investment Research
B17: Report Date | E17: 04-Aug-2026
B18: Version | E18: 1.0
B19: Currency Basis | E19: USD, millions unless per-share
B20: Fiscal Basis | E20: Continuing Operations (ex-Russia), restated FY2021 comparability
A24: NAVIGATION
B26: -> Instructions | G26: -> Raw Financial Data
B27: -> Historical Financial Statements | G27: -> Assumptions
B28: -> Revenue Forecast | G28: -> Operating Forecast
B29: -> DCF Valuation | G29: -> Trading Comparables
B30: -> Sensitivity Analysis | G30: -> Executive Dashboard
B31: -> Banglalink Strategic Insights | G31: -> Investment Summary
A40: This workbook is prepared for independent research and educational purposes based on publicly available information. It does not constitute investment advice, a recommendation, or a solicitation to buy or sell any security. Certain FY2022/FY2023 net income figures remain subject to verification against VEON's primary SEC filings (see Historical Financial Statements).

Sheet Instructions
A1: INSTRUCTIONS & MODEL GUIDE
A3: COLOUR LEGEND
A4: Blue font | B4: Hardcoded input — analyst entry point
A5: Black font | B5: Formula — calculated within the same sheet
A6: Green font | B6: Link — value pulled from another worksheet
A7: Red font | B7: External link or unresolved data-quality flag
A8: Yellow fill | B8: Key assumption — requires periodic review
A10: WORKSHEET GUIDE
A11: Cover | B11: Title page and navigation index.
A12: Raw Financial Data | B12: Unadjusted source data staging area, cited to filings.
A13: Historical Financial Statements | B13: Standardized 5-year IS / BS / CF, linked from Raw Data.
A14: Assumptions | B14: Central driver sheet for all forecast and WACC inputs.
A15: Revenue Forecast | B15: Segment-level revenue build, FY2026E-FY2030E.
A16: Operating Forecast | B16: EBITDA, D&A, CapEx and unlevered FCF build.
A17: DCF Valuation | B17: Discounted cash flow to enterprise and equity value.
A18: Trading Comparables | B18: Peer multiple benchmarking (EV/EBITDA, EV/Sales, P/E).
A19: Sensitivity Analysis | B19: Two-way sensitivity tables and tornado ranking.
A20: Executive Dashboard | B20: One-page KPI and chart summary for IC presentation.
A21: Banglalink Strategic Insights | B21: Bangladesh operating company deep-dive.
A22: Investment Summary | B22: Rating, target price and thesis conclusion.
A24: DATA SOURCES
A25: - VEON Ltd. Form 20-F Annual Reports (SEC filings, FY2021-FY2025)
A26: - VEON Ltd. quarterly and full-year earnings releases and investor presentations
A27: - VEON Integrated Annual Reports (2023, 2024, 2025)
A28: - VEON Dutch Statutory Annual Report (2023)
A29: - Nasdaq, Yahoo Finance (market data)
A31: KNOWN LIMITATIONS
A32: FY2022 net income is subject to conflicting public data (loss vs. profit reported across sources) and FY2023 net income magnitude requires verification against the FY2023 Form 20-F. See Historical Financial Statements for detail.

Sheet Raw Financial Data
A1: RAW FINANCIAL DATA — UNADJUSTED SOURCE STAGING
A2: Line Item | B2: FY2021 (As-Reported) | C2: FY2021 (Restated) | D2: FY2022 | E2: FY2023 | F2: FY2024 | G2: FY2025 | H2: Source Reference | I2: Source Date
A3: Revenue — Pakistan | C3: 1408 | D3: 1285 | E3: 1119 | F3: 1382 | G3: 1624 | H3: 20-F FY2025, Segment Note | I3: 2026
A4: Revenue — Ukraine | C4: 1055 | D4: 971 | E4: 919 | F4: 925 | G4: 1164 | H4: 20-F FY2025, Segment Note | I4: 2026
A5: Revenue — Kazakhstan | C5: 569 | D5: 636 | E5: 774 | F5: 854 | G5: 816 | H5: 20-F FY2025, Segment Note | I5: 2026
A6: Revenue — Bangladesh | C6: 564 | D6: 576 | E6: 570 | F6: 520 | G6: 460 | H6: 20-F FY2025, Segment Note | I6: 2026
A7: Revenue — Uzbekistan | C7: 194 | D7: 233 | E7: 268 | F7: 273 | G7: 308 | H7: 20-F FY2025, Segment Note | I7: 2026
A8: Revenue — Other / HQ | C8: 60 | D8: 54 | E8: 48 | F8: 50 | G8: 27 | H8: 20-F FY2025, Segment Note | I8: 2026
A9: Total Revenue (Check) | B9: 7788 | C9: =SUM(C3:C8) -> 3850 | D9: =SUM(D3:D8) -> 3755 | E9: =SUM(E3:E8) -> 3698 | F9: =SUM(F3:F8) -> 4004 | G9: =SUM(G3:G8) -> 4399
A11: EBITDA — Group (Continuing Ops) | B11: 3332 | C11: 1840 | D11: 1747 | E11: 1612 | F11: 1691 | G11: 2009
A12: Operating Income | C12: 1023 | D12: 1163 | E12: 929 | F12: 1110 | G12: 1439
A13: Net Income — Continuing Operations | B13: 801 | D13: SEE NOTE | E13: SEE NOTE | F13: 487 | G13: 591
A14: CapEx | B14: 1826 | C14: 699 | D14: 634 | E14: 531 | F14: 627 | G14: 733
A15: Free Cash Flow | C15: 1939 | D15: 1923 | E15: 1580 | F15: 523 | G15: 620
A16: Net Debt | C16: 8394 | D16: 5073 | E16: 3254 | F16: 3005 | G16: 3413
A17: Shares Outstanding (million) | G17: 1849.2
A19: ERROR CHECK: Segment Sum = Total Reported
C20: =IF(SUM(C3:C8)=C9,"OK","CHECK") -> OK | D20: =IF(SUM(D3:D8)=D9,"OK","CHECK") -> OK | E20: =IF(SUM(E3:E8)=E9,"OK","CHECK") -> OK | F20: =IF(SUM(F3:F8)=F9,"OK","CHECK") -> OK

Sheet Historical Financial Statements
A1: HISTORICAL FINANCIAL STATEMENTS — FY2021-FY2025 (CONTINUING OPERATIONS)
A3: Line Item | B3: FY2021 | C3: FY2022 | D3: FY2023 | E3: FY2024 | F3: FY2025 | G3: 5-Yr CAGR
A4: INCOME STATEMENT
A5: Revenue | B5: ='Raw Financial Data'!C9 -> 3850 | C5: ='Raw Financial Data'!D9 -> 3755 | D5: ='Raw Financial Data'!E9 -> 3698 | E5: ='Raw Financial Data'!F9 -> 4004 | F5: ='Raw Financial Data'!G9 -> 4399 | G5: =IFERROR((F5/B5)^(1/4)-1,"n/a") -> 0.033887556
A6: Revenue Growth % | C6: =IFERROR(C5/B5-1,"n/a") -> -0.024675325 | D6: =IFERROR(D5/C5-1,"n/a") -> -0.01517976 | E6: =IFERROR(E5/D5-1,"n/a") -> 0.082747431 | F6: =IFERROR(F5/E5-1,"n/a") -> 0.098651349
A7: EBITDA | B7: ='Raw Financial Data'!C11 -> 1840 | C7: ='Raw Financial Data'!D11 -> 1747 | D7: ='Raw Financial Data'!E11 -> 1612 | E7: ='Raw Financial Data'!F11 -> 1691 | F7: ='Raw Financial Data'!G11 -> 2009 | G7: =IFERROR((F7/B7)^(1/4)-1,"n/a") -> 0.022210949
A8: EBITDA Margin % | B8: =B7/B5 -> 0.47792208 | C8: =C7/C5 -> 0.46524634 | D8: =D7/D5 -> 0.4359113 | E8: =E7/E5 -> 0.42232767 | F8: =F7/F5 -> 0.4566947
A9: Operating Income (EBIT) | B9: ='Raw Financial Data'!C12 -> 1023 | C9: ='Raw Financial Data'!D12 -> 1163 | D9: ='Raw Financial Data'!E12 -> 929 | E9: ='Raw Financial Data'!F12 -> 1110 | F9: ='Raw Financial Data'!G12 -> 1439 | G9: =IFERROR((F9/B9)^(1/4)-1,"n/a") -> 0.089046165
A10: Operating Margin % | B10: =B9/B5 -> 0.26571429 | C10: =C9/C5 -> 0.30972037 | D10: =D9/D5 -> 0.25121687 | E10: =E9/E5 -> 0.27722278 | F10: =F9/F5 -> 0.3271198
A11: Net Income (Total) | B11: ='Raw Financial Data'!B13 -> 801 | C11: SEE NOTE 1 | D11: SEE NOTE 2 | E11: ='Raw Financial Data'!F13 -> 487 | F11: ='Raw Financial Data'!G13 -> 591
A13: CASH FLOW
A14: CapEx | B14: ='Raw Financial Data'!C14 -> 699 | C14: ='Raw Financial Data'!D14 -> 634 | D14: ='Raw Financial Data'!E14 -> 531 | E14: ='Raw Financial Data'!F14 -> 627 | F14: ='Raw Financial Data'!G14 -> 733 | G14: =IFERROR((F14/B14)^(1/4)-1,"n/a") -> 0.011944513
A15: Free Cash Flow | B15: ='Raw Financial Data'!C15 -> 1939 | C15: ='Raw Financial Data'!D15 -> 1923 | D15: ='Raw Financial Data'!E15 -> 1580 | E15: ='Raw Financial Data'!F15 -> 523 | F15: ='Raw Financial Data'!G15 -> 620 | G15: =IFERROR((F15/B15)^(1/4)-1,"n/a") -> -0.24802488
A16: FCF Margin % | B16: =B15/B5 -> 0.50363636 | C16: =C15/C5 -> 0.51211718 | D16: =D15/D5 -> 0.42725798 | E16: =E15/E5 -> 0.13061938 | F16: =F15/F5 -> 0.14094112
A18: BALANCE SHEET (SUMMARY)
A19: Net Debt | B19: ='Raw Financial Data'!C16 -> 8394 | C19: ='Raw Financial Data'!D16 -> 5073 | D19: ='Raw Financial Data'!E16 -> 3254 | E19: ='Raw Financial Data'!F16 -> 3005 | F19: ='Raw Financial Data'!G16 -> 3413 | G19: =IFERROR((F19/B19)^(1/4)-1,"n/a") -> -0.20146891
A20: Net Debt / EBITDA (x) | B20: =B19/B7 -> 4.5619565 | C20: =C19/C7 -> 2.9038351 | D20: =D19/D7 -> 2.0186104 | E20: =E19/E7 -> 1.777055 | F20: =F19/F7 -> 1.6988552
A22: NOTE 1 (FY2022 Net Income): | B22: Unresolved — conflicting public sources (loss of ~$818M vs. profit of ~$802M). Verify vs. FY2022 Form 20-F.
A23: NOTE 2 (FY2023 Net Income): | B23: Large loss confirmed (~$3.7B Russia divestiture loss in discontinued ops); precise consolidated figure requires FY2023 Form 20-F verification.
A25: ERROR CHECK: Margin within 0%-60% bound
B26: =IF(AND(B8>=0,B8<=0.6),"OK","REVIEW") -> OK | C26: =IF(AND(C8>=0,C8<=0.6),"OK","REVIEW") -> OK | D26: =IF(AND(D8>=0,D8<=0.6),"OK","REVIEW") -> OK | E26: =IF(AND(E8>=0,E8<=0.6),"OK","REVIEW") -> OK | F26: =IF(AND(F8>=0,F8<=0.6),"OK","REVIEW") -> OK

Sheet Assumptions
A1: ASSUMPTIONS — FORECAST & DISCOUNT RATE DRIVERS
A2: ANALYST INPUT REQUIRED — cells below are intentionally blank pending management guidance / analyst view. Do not populate with estimated figures without explicit sourcing.
A3: Driver | B3: FY2026E | C3: FY2027E | D3: FY2028E | E3: FY2029E | F3: FY2030E
A4: REVENUE GROWTH % (BY SEGMENT)
A5: Pakistan
A6: Ukraine
A7: Kazakhstan
A8: Bangladesh
A9: Uzbekistan
A10: Other / HQ
A12: EBITDA MARGIN TARGET % (BY SEGMENT)
A13: Pakistan
A14: Ukraine
A15: Kazakhstan
A16: Bangladesh
... A25: WACC COMPONENTS
A26: Risk-Free Rate | B26: 0
A27: Equity Risk Premium | B27: 0
A28: Blended Country Risk Premium | B28: 0
A29: Levered Beta | B29: 0
A30: Cost of Equity | B30: =B26+B29*B27+B28 -> 0
A31: Pre-Tax Cost of Debt | B31: 0
A32: Tax Rate (for shield) | B32: 0
A33: After-Tax Cost of Debt | B33: =B31*(1-B32) -> 0
A34: Target Debt / (Debt+Equity) | B34: 0
A35: Target Equity / (Debt+Equity) | B35: =1-B34 -> 1
A36: WACC | B36: =B30*B35+B33*B34 -> 0
A38: Terminal Growth Rate
A39: ERROR CHECK: WACC > Terminal Growth | B39: =IF(B36>B38,"OK","ERROR: WACC<=g") -> ERROR: WACC<=g
A41: FX ASSUMPTIONS (LOCAL CURRENCY PER USD)
A42: PKR/USD Forward Rate
A43: UAH/USD Forward Rate
A44: KZT/USD Forward Rate
A45: BDT/USD Forward Rate
A46: UZS/USD Forward Rate
A49: WACC BUILD-UP (WATERFALL DATA)
A50: Base (invisible) | B50: Value
A51: Cost of Equity (wtd) | B51: 0 | C51: =B30*B35 -> 0
A52: Cost of Debt (wtd, after-tax) | B52: =C51 -> 0 | C52: =B33*B34 -> 0
A53: WACC (Total) | B53: 0 | C53: =B36 -> 0

Sheet Revenue Forecast
A1: REVENUE FORECAST — SEGMENT BUILD (FY2025A-FY2030E)
A2: Segment | B2: FY2025A | C2: FY2026E | D2: FY2027E | E2: FY2028E | F2: FY2029E | G2: FY2030E
A3: Pakistan | B3: ='Raw Financial Data'!G3 -> 1624 | C3: =B3*(1+Assumptions!B5) -> 1624 | D3: =C3*(1+Assumptions!C5) -> 1624 | E3: =D3*(1+Assumptions!D5) -> 1624 | F3: =E3*(1+Assumptions!E5) -> 1624 | G3: =F3*(1+Assumptions!F5) -> 1624
A4: Ukraine | B4: ='Raw Financial Data'!G4 -> 1164 | C4: =B4*(1+Assumptions!B6) -> 1164 | D4: =C4*(1+Assumptions!C6) -> 1164 | E4: =D4*(1+Assumptions!D6) -> 1164 | F4: =E4*(1+Assumptions!E6) -> 1164 | G4: =F4*(1+Assumptions!F6) -> 1164
A5: Kazakhstan | B5: ='Raw Financial Data'!G5 -> 816 | C5: =B5*(1+Assumptions!B7) -> 816 | D5: =C5*(1+Assumptions!C7) -> 816 | E5: =D5*(1+Assumptions!D7) -> 816 | F5: =E5*(1+Assumptions!E7) -> 816 | G5: =F5*(1+Assumptions!F7) -> 816
A6: Bangladesh | B6: ='Raw Financial Data'!G6 -> 460 | C6: =B6*(1+Assumptions!B8) -> 460 | D6: =C6*(1+Assumptions!C8) -> 460 | E6: =D6*(1+Assumptions!D8) -> 460 | F6: =E6*(1+Assumptions!E8) -> 460 | G6: =F6*(1+Assumptions!F8) -> 460
A7: Uzbekistan | B7: ='Raw Financial Data'!G7 -> 308 | C7: =B7*(1+Assumptions!B9) -> 308 | D7: =C7*(1+Assumptions!C9) -> 308 | E7: =D7*(1+Assumptions!D9) -> 308 | F7: =E7*(1+Assumptions!E9) -> 308 | G7: =F7*(1+Assumptions!F9) -> 308
A8: Other / HQ | B8: ='Raw Financial Data'!G8 -> 27 | C8: =B8*(1+Assumptions!B10) -> 27 | D8: =C8*(1+Assumptions!C10) -> 27 | E8: =D8*(1+Assumptions!D10) -> 27 | F8: =E8*(1+Assumptions!E10) -> 27 | G8: =F8*(1+Assumptions!F10) -> 27
A9: Total Revenue | B9: =SUM(B3:B8) -> 4399 | C9: =SUM(C3:C8) -> 4399 | D9: =SUM(D3:D8) -> 4399 | E9: =SUM(E3:E8) -> 4399 | F9: =SUM(F3:F8) -> 4399 | G9: =SUM(G3:G8) -> 4399
A10: YoY Growth % | C10: =C9/B9-1 -> 0 | D10: =D9/C9-1 -> 0 | E10: =E9/D9-1 -> 0 | F10: =F9/E9-1 -> 0 | G10: =G9/F9-1 -> 0
A12: ERROR CHECK: Segment Sum = Total
B13: =IF(ROUND(SUM(B3:B8)-B9,2)=0,"OK","CHECK") -> OK | C13: =IF(ROUND(SUM(C3:C8)-C9,2)=0,"OK","CHECK") -> OK | D13: =IF(ROUND(SUM(D3:D8)-D9,2)=0,"OK","CHECK") -> OK | E13: =IF(ROUND(SUM(E3:E8)-E9,2)=0,"OK","CHECK") -> OK | F13: =IF(ROUND(SUM(F3:F8)-F9,2)=0,"OK","CHECK") -> OK | G13: =IF(ROUND(SUM(G3:G8)-G9,2)=0,"OK","CHECK") -> OK
A15: Digital Revenue (memo) | B15: 759
A16: Digital % of Total Revenue | B16: =B15/B9 -> 0.17253921 | C16: =C15/C9 -> 0 | D16: =D15/D9 -> 0 | E16: =E15/E9 -> 0 | F16: =F15/F9 -> 0 | G16: =G15/G9 -> 0

Sheet Operating Forecast
A1: OPERATING FORECAST — EBITDA, D&A, CAPEX & UNLEVERED FCF
A2: Line Item | B2: FY2025A | C2: FY2026E | D2: FY2027E | E2: FY2028E | F2: FY2029E | G2: FY2030E
A3: Revenue (link) | B3: ='Revenue Forecast'!B9 -> 4399 | C3: ='Revenue Forecast'!C9 -> 4399 | D3: ='Revenue Forecast'!D9 -> 4399 | E3: ='Revenue Forecast'!E9 -> 4399 | F3: ='Revenue Forecast'!F9 -> 4399 | G3: ='Revenue Forecast'!G9 -> 4399
A5: EBITDA BY SEGMENT
A6: Pakistan | B6: =0 -> 0 | C6: ='Revenue Forecast'!C3*Assumptions!B13 -> 0 | D6: ='Revenue Forecast'!D3*Assumptions!C13 -> 0 | E6: ='Revenue Forecast'!E3*Assumptions!D13 -> 0 | F6: ='Revenue Forecast'!F3*Assumptions!E13 -> 0 | G6: ='Revenue Forecast'!G3*Assumptions!F13 -> 0
A7: Ukraine | B7: =0 -> 0 | C7: ='Revenue Forecast'!C4*Assumptions!B14 -> 0 | D7: ='Revenue Forecast'!D4*Assumptions!C14 -> 0 | E7: ='Revenue Forecast'!E4*Assumptions!D14 -> 0 | F7: ='Revenue Forecast'!F4*Assumptions!E14 -> 0 | G7: ='Revenue Forecast'!G4*Assumptions!F14 -> 0
A8: Kazakhstan | B8: =0 -> 0 | C8: ='Revenue Forecast'!C5*Assumptions!B15 -> 0 | D8: ='Revenue Forecast'!D5*Assumptions!C15 -> 0 | E8: ='Revenue Forecast'!E5*Assumptions!D15 -> 0 | F8: ='Revenue Forecast'!F5*Assumptions!E15 -> 0 | G8: ='Revenue Forecast'!G5*Assumptions!F15 -> 0
A9: Bangladesh | B9: =0 -> 0 | C9: ='Revenue Forecast'!C6*Assumptions!B16 -> 0 | D9: ='Revenue Forecast'!D6*Assumptions!C16 -> 0 | E9: ='Revenue Forecast'!E6*Assumptions!D16 -> 0 | F9: ='Revenue Forecast'!F6*Assumptions!E16 -> 0 | G9: ='Revenue Forecast'!G6*Assumptions!F16 -> 0
A10: Uzbekistan | B10: =0 -> 0 | C10: ='Revenue Forecast'!C7*Assumptions!B17 -> 0 | D10: ='Revenue Forecast'!D7*Assumptions!C17 -> 0 | E10: ='Revenue Forecast'!E7*Assumptions!D17 -> 0 | F10: ='Revenue Forecast'!F7*Assumptions!E17 -> 0 | G10: ='Revenue Forecast'!G7*Assumptions!F17 -> 0
A11: Other / HQ | B11: =0 -> 0 | C11: ='Revenue Forecast'!C8*Assumptions!B18 -> 0 | D11: ='Revenue Forecast'!D8*Assumptions!C18 -> 0 | E11: ='Revenue Forecast'!E8*Assumptions!D18 -> 0 | F11: ='Revenue Forecast'!F8*Assumptions!E18 -> 0 | G11: ='Revenue Forecast'!G8*Assumptions!F18 -> 0
A12: Group EBITDA | B12: ='Historical Financial Statements'!F7 -> 2009 | C12: =SUM(C6:C11) -> 0 | D12: =SUM(D6:D11) -> 0 | E12: =SUM(E6:E11) -> 0 | F12: =SUM(F6:F11) -> 0 | G12: =SUM(G6:G11) -> 0
A13: EBITDA Margin % | B13: =B12/B3 -> 0.4566947 | C13: =C12/C3 -> 0 | D13: =D12/D3 -> 0 | E13: =E12/E3 -> 0 | F13: =F12/F3 -> 0 | G13: =G12/G3 -> 0
A14: ERROR CHECK: Margin <= 60% | B14: =IF(B13<=0.6,"OK","REVIEW") -> OK | C14: =IF(C13<=0.6,"OK","REVIEW") -> OK | D14: =IF(D13<=0.6,"OK","REVIEW") -> OK | E14: =IF(E13<=0.6,"OK","REVIEW") -> OK | F14: =IF(F13<=0.6,"OK","REVIEW") -> OK | G14: =IF(G13<=0.6,"OK","REVIEW") -> OK
A16: D&A | B16: =0 -> 0 | C16: =C3*Assumptions!B22 -> 0 | D16: =D3*Assumptions!C22 -> 0 | E16: =E3*Assumptions!D22 -> 0 | F16: =F3*Assumptions!E22 -> 0 | G16: =G3*Assumptions!F22 -> 0
A17: EBIT | B17: =B12-B16 -> 2009 | C17: =C12-C16 -> 0 | D17: =D12-D16 -> 0 | E17: =E12-E16 -> 0 | F17: =F12-F16 -> 0 | G17: =G12-G16 -> 0
A19: CapEx | B19: ='Historical Financial Statements'!F14 -> 733 | C19: =C3*Assumptions!B23 -> 0 | D19: =D3*Assumptions!C23 -> 0 | E19: =E3*Assumptions!D23 -> 0 | F19: =F3*Assumptions!E23 -> 0 | G19: =G3*Assumptions!F23 -> 0
A20: Working Capital Change
A21: Unlevered Free Cash Flow | B21: =B17*(1-Assumptions!B21)+B16-B19-B20 -> 1276 | C21: =C17*(1-Assumptions!B21)+C16-C19-C20 -> 0 | D21: =D17*(1-Assumptions!B21)+D16-D19-D20 -> 0 | E21: =E17*(1-Assumptions!B21)+E16-E19-E20 -> 0 | F21: =F17*(1-Assumptions!B21)+F16-F19-F20 -> 0 | G21: =G17*(1-Assumptions!B21)+G16-G19-G20 -> 0
A24: EBITDA BRIDGE (WATERFALL DATA)
A25: Stage | B25: Base | C25: Delta
A26: FY25A EBITDA | B26: 0 | C26: =B12 -> 2009
A27: Δ Pakistan (FY25A->FY30E) | B27: =MIN(C26,C26+D27) -> 2009 | C27: =ABS(D27) -> 0 | D27: =G6-B6 -> 0
A28: Δ Ukraine (FY25A->FY30E) | B28: =MIN((C26+D27),(C26+D27)+D28) -> 2009 | C28: =ABS(D28) -> 0 | D28: =G7-B7 -> 0
A29: Δ Kazakhstan (FY25A->FY30E) | B29: =MIN(((C26+D27)+D28),((C26+D27)+D28)+D29) -> 2009 | C29: =ABS(D29) -> 0 | D29: =G8-B8 -> 0
A30: Δ Bangladesh (FY25A->FY30E) | B30: =MIN((((C26+D27)+D28)+D29),(((C26+D27)+D28)+D29)+D30) -> 2009 | C30: =ABS(D30) -> 0 | D30: =G9-B9 -> 0
A31: Δ Uzbekistan (FY25A->FY30E) | B31: =MIN(((((C26+D27)+D28)+D29)+D30),((((C26+D27)+D28)+D29)+D30)+D31) -> 2009 | C31: =ABS(D31) -> 0 | D31: =G10-B10 -> 0
A32: FY30E EBITDA | B32: 0 | C32: =G12 -> 0

Sheet DCF Valuation
A1: DCF VALUATION — UNLEVERED FREE CASH FLOW TO FIRM
A3: Line Item | B3: FY2026E | C3: FY2027E | D3: FY2028E | E3: FY2029E | F3: FY2030E | G3: Terminal
A4: Unlevered Free Cash Flow | B4: ='Operating Forecast'!C21 -> 0 | C4: ='Operating Forecast'!D21 -> 0 | D4: ='Operating Forecast'!E21 -> 0 | E4: ='Operating Forecast'!F21 -> 0 | F4: ='Operating Forecast'!G21 -> 0 | G4: =F4*(1+Assumptions!B38) -> 0
A5: Discount Period (n) | B5: =1 -> 1 | C5: =2 -> 2 | D5: =3 -> 3 | E5: =4 -> 4 | F5: =5 -> 5
A6: Discount Factor | B6: =1/(1+Assumptions!$B$36)^B5 -> 1 | C6: =1/(1+Assumptions!$B$36)^C5 -> 1 | D6: =1/(1+Assumptions!$B$36)^D5 -> 1 | E6: =1/(1+Assumptions!$B$36)^E5 -> 1 | F6: =1/(1+Assumptions!$B$36)^F5 -> 1
A7: PV of Free Cash Flow | B7: =B4*B6 -> 0 | C7: =C4*C6 -> 0 | D7: =D4*D6 -> 0 | E7: =E4*E6 -> 0 | F7: =F4*F6 -> 0
A9: Sum of PV — Explicit Period | B9: =SUM(B7:F7) -> 0
A10: Terminal Value (Gordon Growth) | B10: =IFERROR(G4/(Assumptions!$B$36-Assumptions!$B$38),"INPUT REQUIRED") -> INPUT REQUIRED
A11: PV of Terminal Value | B11: =IFERROR(B10*F6,"INPUT REQUIRED") -> INPUT REQUIRED
A13: Enterprise Value | B13: =IFERROR(B9+B11,"INPUT REQUIRED") -> INPUT REQUIRED
A14: Less: Net Debt | B14: =-'Historical Financial Statements'!F19 -> -3413
A15: Less: Minority Interest
A16: Equity Value | B16: =IFERROR(B13+B14-B15,"INPUT REQUIRED") -> INPUT REQUIRED
A17: Diluted Shares Outstanding (mn) | B17: ='Raw Financial Data'!G17 -> 1849.2
A18: Implied Share Price | B18: =IFERROR(B16/B17,"INPUT REQUIRED") -> INPUT REQUIRED
A19: Current Share Price (input)
A20: Implied Upside / (Downside) | B20: =IFERROR(B18/B19-1,"n/a") -> n/a
A22: ERROR CHECK: WACC > Terminal Growth | B22: =IF(Assumptions!$B$36>Assumptions!$B$38,"OK","ERROR") -> ERROR
A25: EV COMPOSITION (CHART DATA)
A26: Component | B26: USD mn
A27: PV of Explicit FCF | B27: =B9 -> 0
A28: PV of Terminal Value | B28: =IFERROR(B11,"INPUT REQUIRED") -> INPUT REQUIRED

Sheet Trading Comparables
A1: TRADING COMPARABLES — PEER BENCHMARKING
A2: ANALYST INPUT REQUIRED — peer market data must be sourced live from Nasdaq / Yahoo Finance / Bloomberg prior to use. No figures estimated.
A3: Company | B3: Ticker | C3: Market Cap | D3: Net Debt | E3: EV | F3: Revenue | G3: EBITDA | H3: EV/EBITDA | I3: EV/Sales | J3: P/E
A4: Turkcell | B4: TKC | E4: =C4+D4 -> 0 | H4: =IFERROR(E4/G4,"n/a") -> n/a | I4: =IFERROR(E4/F4,"n/a") -> n/a
A5: MTN Group | B5: MTN.JO | E5: =C5+D5 -> 0 | H5: =IFERROR(E5/G5,"n/a") -> n/a | I5: =IFERROR(E5/F5,"n/a") -> n/a
A6: Millicom | B6: TIGO | E6: =C6+D6 -> 0 | H6: =IFERROR(E6/G6,"n/a") -> n/a | I6: =IFERROR(E6/F6,"n/a") -> n/a
A7: Ooredoo | B7: ORDS.QA | E7: =C7+D7 -> 0 | H7: =IFERROR(E7/G7,"n/a") -> n/a | I7: =IFERROR(E7/F7,"n/a") -> n/a
A8: Telenor | B8: TEL.OL | E8: =C8+D8 -> 0 | H8: =IFERROR(E8/G8,"n/a") -> n/a | I8: =IFERROR(E8/F8,"n/a") -> n/a
A9: Axiata | B9: AXIATA.KL | E9: =C9+D9 -> 0 | H9: =IFERROR(E9/G9,"n/a") -> n/a | I9: =IFERROR(E9/F9,"n/a") -> n/a
A10: e& | B10: EAND.AD | E10: =C10+D10 -> 0 | H10: =IFERROR(E10/G10,"n/a") -> n/a | I10: =IFERROR(E10/F10,"n/a") -> n/a
A11: Zain Group | B11: ZAIN.KW | E11: =C11+D11 -> 0 | H11: =IFERROR(E11/G11,"n/a") -> n/a | I11: =IFERROR(E11/F11,"n/a") -> n/a
A12: VEON Ltd. | B12: VEON | D12: ='Historical Financial Statements'!F19 -> 3413 | E12: =C12+D12 -> 3413 | F12: ='Historical Financial Statements'!F5 -> 4399 | G12: ='Historical Financial Statements'!F7 -> 2009 | H12: =IFERROR(E12/G12,"n/a") -> 1.6988552 | I12: =IFERROR(E12/F12,"n/a") -> 0.77585815
A14: Peer Median | H14: =IFERROR(MEDIAN(H4:H11),"INPUT REQUIRED") -> INPUT REQUIRED | I14: =IFERROR(MEDIAN(I4:I11),"INPUT REQUIRED") -> INPUT REQUIRED | J14: =IFERROR(MEDIAN(J4:J11),"INPUT REQUIRED") -> INPUT REQUIRED
A15: Peer Average | H15: =IFERROR(AVERAGE(H4:H11),"INPUT REQUIRED") -> INPUT REQUIRED | I15: =IFERROR(AVERAGE(I4:I11),"INPUT REQUIRED") -> INPUT REQUIRED | J15: =IFERROR(AVERAGE(J4:J11),"INPUT REQUIRED") -> INPUT REQUIRED
A17: Implied VEON EV (EV/EBITDA basis) | B17: =IFERROR(G12*H14,"INPUT REQUIRED") -> INPUT REQUIRED
A18: ERROR CHECK: Outlier Flag (>2x Median)
H19: =IFERROR(IF(COUNTIF(H4:H11,">"&2*H14)>0,"OUTLIER PRESENT","OK"),"INPUT REQUIRED") -> OK | I19: =IFERROR(IF(COUNTIF(I4:I11,">"&2*I14)>0,"OUTLIER PRESENT","OK"),"INPUT REQUIRED") -> OK

Sheet Sensitivity Analysis
A1: SENSITIVITY ANALYSIS — IMPLIED SHARE PRICE
A3: Implied Share Price ($) — WACC (rows) x Terminal Growth (columns)
A4: WACC \ Term. g | B4: =Assumptions!$B$38+(-0.01) -> -0.01 | C4: =Assumptions!$B$38+(-0.005) -> -0.005 | D4: =Assumptions!$B$38+(0) -> 0 | E4: =Assumptions!$B$38+(0.005) -> 0.005 | F4: =Assumptions!$B$38+(0.01) -> 0.01
A5: =Assumptions!$B$36+(-0.02) -> -0.02 | B5: =IFERROR((NPV($A5,'DCF Valuation'!$B$4:$F$4)+('DCF Valuation'!$G$4/($A5-B$4))/(1+$A5)^5+'DCF Valuation'!$B$14-'DCF Valuation'!$B$15)/'DCF Valuation'!$B$17,"n/a") -> -1.845663 | C5: =IFERROR((NPV($A5,'DCF Valuation'!$B$4:$F$4)+('DCF Valuation'!$G$4/($A5-C$4))/(1+$A5)^5+'DCF Valuation'!$B$14-'DCF Valuation'!$B$15)/'DCF Valuation'!$B$17,"n/a") -> -1.845663 | D5: =IFERROR((NPV($A5,'DCF Valuation'!$B$4:$F$4)+('DCF Valuation'!$G$4/($A5-D$4))/(1+$A5)^5+'DCF Valuation'!$B$14-'DCF Valuation'!$B$15)/'DCF Valuation'!$B$17,"n/a") -> -1.845663 | E5: =IFERROR((NPV($A5,'DCF Valuation'!$B$4:$F$4)+('DCF Valuation'!$G$4/($A5-E$4))/(1+$A5)^5+'DCF Valuation'!$B$14-'DCF Valuation'!$B$15)/'DCF Valuation'!$B$17,"n/a") -> -1.845663 | F5: =IFERROR((NPV($A5,'DCF Valuation'!$B$4:$F$4)+('DCF Valuation'!$G$4/($A5-F$4))/(1+$A5)^5+'DCF Valuation'!$B$14-'DCF Valuation'!$B$15)/'DCF Valuation'!$B$17,"n/a") -> -1.845663
A6: =Assumptions!$B$36+(-0.01) -> -0.01 | B6: =IFERROR((NPV($A6,'DCF Valuation'!$B$4:$F$4)+('DCF Valuation'!$G$4/($A6-B$4))/(1+$A6)^5+'DCF Valuation'!$B$14-'DCF Valuation'!$B$15)/'DCF Valuation'!$B$17,"n/a") -> n/a | C6: =IFERROR((NPV($A6,'DCF Valuation'!$B$4:$F$4)+('DCF Valuation'!$G$4/($A6-C$4))/(1+$A6)^5+'DCF Valuation'!$B$14-'DCF Valuation'!$B$15)/'DCF Valuation'!$B$17,"n/a") -> -1.845663 | D6: =IFERROR((NPV($A6,'DCF Valuation'!$B$4:$F$4)+('DCF Valuation'!$G$4/($A6-D$4))/(1+$A6)^5+'DCF Valuation'!$B$14-'DCF Valuation'!$B$15)/'DCF Valuation'!$B$17,"n/a") -> -1.845663 | E6: =IFERROR((NPV($A6,'DCF Valuation'!$B$4:$F$4)+('DCF Valuation'!$G$4/($A6-E$4))/(1+$A6)^5+'DCF Valuation'!$B$14-'DCF Valuation'!$B$15)/'DCF Valuation'!$B$17,"n/a") -> -1.845663 | F6: =IFERROR((NPV($A6,'DCF Valuation'!$B$4:$F$4)+('DCF Valuation'!$G$4/($A6-F$4))/(1+$A6)^5+'DCF Valuation'!$B$14-'DCF Valuation'!$B$15)/'DCF Valuation'!$B$17,"n/a") -> -1.845663
A7: =Assumptions!$B$36+(0) -> 0 | B7: =IFERROR((NPV($A7,'DCF Valuation'!$B$4:$F$4)+('DCF Valuation'!$G$4/($A7-B$4))/(1+$A7)^5+'DCF Valuation'!$B$14-'DCF Valuation'!$B$15)/'DCF Valuation'!$B$17,"n/a") -> -1.845663 | C7: =IFERROR((NPV($A7,'DCF Valuation'!$B$4:$F$4)+('DCF Valuation'!$G$4/($A7-C$4))/(1+$A7)^5+'DCF Valuation'!$B$14-'DCF Valuation'!$B$15)/'DCF Valuation'!$B$17,"n/a") -> -1.845663 | D7: =IFERROR((NPV($A7,'DCF Valuation'!$B$4:$F$4)+('DCF Valuation'!$G$4/($A7-D$4))/(1+$A7)^5+'DCF Valuation'!$B$14-'DCF Valuation'!$B$15)/'DCF Valuation'!$B$17,"n/a") -> n/a | E7: =IFERROR((NPV($A7,'DCF Valuation'!$B$4:$F$4)+('DCF Valuation'!$G$4/($A7-E$4))/(1+$A7)^5+'DCF Valuation'!$B$14-'DCF Valuation'!$B$15)/'DCF Valuation'!$B$17,"n/a") -> -1.845663 | F7: =IFERROR((NPV($A7,'DCF Valuation'!$B$4:$F$4)+('DCF Valuation'!$G$4/($A7-F$4))/(1+$A7)^5+'DCF Valuation'!$B$14-'DCF Valuation'!$B$15)/'DCF Valuation'!$B$17,"n/a") -> -1.845663
A8: =Assumptions!$B$36+(0.01) -> 0.01 | B8: =IFERROR((NPV($A8,'DCF Valuation'!$B$4:$F$4)+('DCF Valuation'!$G$4/($A8-B$4))/(1+$A8)^5+'DCF Valuation'!$B$14-'DCF Valuation'!$B$15)/'DCF Valuation'!$B$17,"n/a") -> -1.845663 | C8: =IFERROR((NPV($A8,'DCF Valuation'!$B$4:$F$4)+('DCF Valuation'!$G$4/($A8-C$4))/(1+$A8)^5+'DCF Valuation'!$B$14-'DCF Valuation'!$B$15)/'DCF Valuation'!$B$17,"n/a") -> -1.845663 | D8: =IFERROR((NPV($A8,'DCF Valuation'!$B$4:$F$4)+('DCF Valuation'!$G$4/($A8-D$4))/(1+$A8)^5+'DCF Valuation'!$B$14-'DCF Valuation'!$B$15)/'DCF Valuation'!$B$17,"n/a") -> -1.845663 | E8: =IFERROR((NPV($A8,'DCF Valuation'!$B$4:$F$4)+('DCF Valuation'!$G$4/($A8-E$4))/(1+$A8)^5+'DCF Valuation'!$B$14-'DCF Valuation'!$B$15)/'DCF Valuation'!$B$17,"n/a") -> -1.845663 | F8: =IFERROR((NPV($A8,'DCF Valuation'!$B$4:$F$4)+('DCF Valuation'!$G$4/($A8-F$4))/(1+$A8)^5+'DCF Valuation'!$B$14-'DCF Valuation'!$B$15)/'DCF Valuation'!$B$17,"n/a") -> n/a
A9: =Assumptions!$B$36+(0.02) -> 0.02 | B9: =IFERROR((NPV($A9,'DCF Valuation'!$B$4:$F$4)+('DCF Valuation'!$G$4/($A9-B$4))/(1+$A9)^5+'DCF Valuation'!$B$14-'DCF Valuation'!$B$15)/'DCF Valuation'!$B$17,"n/a") -> -1.845663 | C9: =IFERROR((NPV($A9,'DCF Valuation'!$B$4:$F$4)+('DCF Valuation'!$G$4/($A9-C$4))/(1+$A9)^5+'DCF Valuation'!$B$14-'DCF Valuation'!$B$15)/'DCF Valuation'!$B$17,"n/a") -> -1.845663 | D9: =IFERROR((NPV($A9,'DCF Valuation'!$B$4:$F$4)+('DCF Valuation'!$G$4/($A9-D$4))/(1+$A9)^5+'DCF Valuation'!$B$14-'DCF Valuation'!$B$15)/'DCF Valuation'!$B$17,"n/a") -> -1.845663 | E9: =IFERROR((NPV($A9,'DCF Valuation'!$B$4:$F$4)+('DCF Valuation'!$G$4/($A9-E$4))/(1+$A9)^5+'DCF Valuation'!$B$14-'DCF Valuation'!$B$15)/'DCF Valuation'!$B$17,"n/a") -> -1.845663 | F9: =IFERROR((NPV($A9,'DCF Valuation'!$B$4:$F$4)+('DCF Valuation'!$G$4/($A9-F$4))/(1+$A9)^5+'DCF Valuation'!$B$14-'DCF Valuation'!$B$15)/'DCF Valuation'!$B$17,"n/a") -> -1.845663
A12: TORNADO SENSITIVITY — IMPLIED PRICE RANGE BY DRIVER
A13: Driver | B13: Low Case ($) | C13: Base Case ($) | D13: High Case ($) | E13: Range ($)
A14: WACC (+/-2.0%) | B14: =IFERROR(MIN(B5:F9),"INPUT REQUIRED") -> -1.845663 | C14: =IFERROR('DCF Valuation'!$B$18,"INPUT REQUIRED") -> INPUT REQUIRED | D14: =IFERROR(MAX(B5:F9),"INPUT REQUIRED") -> -1.845663 | E14: =IFERROR(D14-B14,"INPUT REQUIRED") -> 0
A15: Terminal Growth (+/-1.0%) | B15: =IFERROR(MIN(B5:F9),"INPUT REQUIRED") -> -1.845663 | C15: =IFERROR('DCF Valuation'!$B$18,"INPUT REQUIRED") -> INPUT REQUIRED | D15: =IFERROR(MAX(B5:F9),"INPUT REQUIRED") -> -1.845663 | E15: =IFERROR(D15-B15,"INPUT REQUIRED") -> 0
A16: Digital Margin Assumption | B16: =IFERROR(MIN(B5:F9),"INPUT REQUIRED") -> -1.845663 | C16: =IFERROR('DCF Valuation'!$B$18,"INPUT REQUIRED") -> INPUT REQUIRED | D16: =IFERROR(MAX(B5:F9),"INPUT REQUIRED") -> -1.845663 | E16: =IFERROR(D16-B16,"INPUT REQUIRED") -> 0
A17: FX (Local Currency Basket) | B17: =IFERROR(MIN(B5:F9),"INPUT REQUIRED") -> -1.845663 | C17: =IFERROR('DCF Valuation'!$B$18,"INPUT REQUIRED") -> INPUT REQUIRED | D17: =IFERROR(MAX(B5:F9),"INPUT REQUIRED") -> -1.845663 | E17: =IFERROR(D17-B17,"INPUT REQUIRED") -> 0

Sheet Executive Dashboard
A1: VEON Ltd. (NASDAQ: VEON) — Executive Dashboard | K1: ="As of: "&Cover!E17 -> As of: 04-Aug-2026 | O1: OVERWEIGHT (SELECTIVE)
A4: ● MARKET CAP | E4: ● ENTERPRISE VALUE | I4: ● TARGET PRICE / UPSIDE | M4: ● NET DEBT | Q4: ● NET LEVERAGE
A6: ='Trading Comparables'!C12 -> 0 | E6: =IFERROR('DCF Valuation'!B13,"INPUT REQUIRED") -> INPUT REQUIRED | I6: =IFERROR('DCF Valuation'!B18,"INPUT REQUIRED") -> INPUT REQUIRED | M6: ='Historical Financial Statements'!F19 -> 3413 | Q6: ='Historical Financial Statements'!F20 -> 1.6988552
A9: ● REVENUE CAGR (FY21-25) | E9: ● EBITDA MARGIN (FY25) | I9: ● FREE CASH FLOW (FY25) | M9: ● ROIC (TTM) | Q9: ● ROE (TTM)
A11: ='Historical Financial Statements'!G5 -> 0.033887556 | E11: ='Historical Financial Statements'!F8 -> 0.4566947 | I11: ='Historical Financial Statements'!F15 -> 620 | M11: 0.195 | Q11: 0.409
A14: =IFERROR("Rating: OVERWEIGHT (SELECTIVE) | Target Price: $"&TEXT('DCF Valuation'!B18,"0.00")&" | Thesis: Digital-mix inflection, Kyivstar listing provides SOTP price discovery, balance sheet materially de-levered vs. FY2021; Ukraine war-risk and FCF conversion remain key watch items.","INPUT REQUIRED") -> Rating: OVERWEIGHT (SELECTIVE) | Target Price: $INPUT REQUIRED | Thesis: Digital-mix inflection, Kyivstar listing provides SOTP price discovery, balance sheet materially de-levered vs. FY2021; Ukraine war-risk and FCF conversion remain key watch items.
A46: Share Price Input Row (populate from Nasdaq)
A47: Method | B47: Low Base | C47: Range
A48: DCF | B48: 0 | C48: =IFERROR('DCF Valuation'!$B$18,"INPUT REQUIRED") -> INPUT REQUIRED
A49: EV/EBITDA Comps | B49: 0 | C49: 0
A50: EV/Sales Comps | B50: 0 | C50: 0
A51: 52-Wk Trading Range | B51: 0 | C51: 0

Sheet Banglalink Strategic Insights
A1: BANGLALINK STRATEGIC INSIGHTS — BANGLADESH OPERATING COMPANY
A3: SEGMENT FINANCIAL SNAPSHOT
A4: Metric | B4: FY2021 | C4: FY2022 | D4: FY2023 | E4: FY2024 | F4: FY2025
A5: Bangladesh Revenue (USD mn) | B5: ='Raw Financial Data'!C6 -> 564 | C5: ='Raw Financial Data'!D6 -> 576 | D5: ='Raw Financial Data'!E6 -> 570 | E5: ='Raw Financial Data'!F6 -> 520 | F5: ='Raw Financial Data'!G6 -> 460
A6: YoY Growth % | C6: =C5/B5-1 -> 0.021276596 | D6: =D5/C5-1 -> -0.010416667 | E6: =E5/D5-1 -> -0.087719298 | F6: =F5/E5-1 -> -0.11538462
A8: STRATEGIC CAPITAL COMMITMENT
A9: Anchor Investment (June 2026, USD mn) | B9: 250
A10: Targeted Follow-On Capital (USD mn) | B10: 1000
A11: Capital Multiplier (x) | B11: =B10/B9 -> 4
A13: DIGITAL ENGAGEMENT — TOFFEE PLATFORM
A14: Event | B14: Viewers / MAU (mn)
A15: World Cup 2022 Final (single match) | B15: 15
A16: World Cup 2026 (39-day tournament, MAU) | B16: 20
A17: Live Watch Minutes, WC2026 (billion) | B17: 2
A18: Peak Concurrent Viewers, WC2026 (mn) | B18: 1.5
A20: FINTECH & GROUP DIGITAL METRICS
A21: Group Financial Services MAU (mn) | B21: 21.6
A22: Digital Banking License Status | B22: Applied — Pending
A24: GROWTH DRIVERS (QUALITATIVE)
A25: - Digital banking license resolution
A26: - Toffee mega-event MAU and advertising monetization
A27: - RYZE AI-personalization and youth ARPU deepening
A28: - Direct-to-cell satellite connectivity (rural reach)
A29: - Diversification into education, healthcare, agriculture, IoT

Sheet Investment Summary
A1: INVESTMENT SUMMARY
A3: Rating | B3: OVERWEIGHT (SELECTIVE)
A4: Target Price | B4: =IFERROR('DCF Valuation'!B18,"INPUT REQUIRED") -> INPUT REQUIRED
A5: Current Price (input) | B5: ='DCF Valuation'!B19 -> 0
A6: Implied Upside / (Downside) | B6: ='DCF Valuation'!B20 -> n/a
A8: BULL CASE
A9: - | B9: Digital revenue reached 20.1% of Group revenue in 4Q25 (+84.1% YoY) — mix shift not yet fully priced.
A10: - | B10: Kyivstar's standalone Nasdaq listing enables direct sum-of-the-parts value verification.
A11: - | B11: Net debt reduced from $8,394M (FY2021) to $3,413M (FY2025) — substantial balance sheet repair.
A12: - | B12: Capital return commitments ($100M/yr minimum, $139M cumulative buybacks since Aug-2024).
A13: - | B13: Banglalink anchor investment ($250M targeting $1B follow-on) signals conviction in optionality.
A15: BEAR CASE
A16: - | B16: Ukraine exposure represents structural, largely unhedgeable nationalization risk.
A17: - | B17: FCF conversion has not recovered to FY2021-22 levels (margin ~50% -> ~13-14%).
A18: - | B18: LetterOne's concentrated 45.5% ownership carries governance/regulatory overhang risk.
A19: - | B19: Bangladesh and Pakistan carry recurring political-instability and network-disruption risk.
A20: - | B20: FY2022/FY2023 net income figures show unresolved discrepancies pending 20-F verification.
A22: KEY CATALYSTS
A23: - | B23: Continued digital-revenue mix expansion beyond 20% quarterly threshold
A24: - | B24: Kyivstar equity value discovery relative to consolidated EV
A25: - | B25: Execution against $100M minimum annual shareholder return commitment
A26: - | B26: Regulatory clarity on Ukrainian nationalization-risk legislation
A27: - | B27: Resolution of Banglalink's digital banking license application
A28: - | B28: Confirmation of FY2025 Form 20-F figures and FY22/23 net income reconciliation
A31: TARGET PRICE DERIVATION (CHART DATA)
A32: Method | B32: Value ($)
A33: DCF Value | B33: =IFERROR('DCF Valuation'!B18,"INPUT REQUIRED") -> INPUT REQUIRED
A34: Trading Comps Implied | B34: =IFERROR('Trading Comparables'!B33/'DCF Valuation'!B17,"n/a") -> 0
A35: Blended Target | B35: =IFERROR('DCF Valuation'!B18,"INPUT REQUIRED") -> INPUT REQUIRED
A37: DISCLAIMER
A38: This workbook is prepared for independent research and educational purposes based on publicly available information. It does not represent the views, research, or output of any employer, institution, or investment bank. It does not constitute investment advice, a recommendation, or a solicitation to buy or sell any security. Readers should consult a licensed financial advisor before making investment decisions. Certain FY2022/FY2023 net income figures require verification against VEON's primary SEC filings.
